Workbook

Sheet README
A1: TEMPLATE ANALISIS LK ASURANSI UMUM – IFRS 9 / IFRS 17 (VERSI KONVERSI)
A3: Tujuan | B3: Template ini dibuat untuk audited report perusahaan asuransi umum yang menyusun laporan berdasarkan IFRS 9 / PSAK 109 dan IFRS 17 / PSAK 117. Struktur dibuat generik sehingga pengguna cukup memetakan akun audited report ke baris input yang paling sesuai.
A5: Cakupan | B5: Mencakup entitas asuransi umum konvensional, syariah, atau campuran. Fokus utama pada underwriting result, loss ratio, expense ratio, combined ratio, cadangan klaim, dan ketergantungan reasuransi.
A7: Cara pakai ringkas | B7: 1) Isi Setup. 2) Isi sel kuning pada Input_SFP, Input_PL_OCI, Input_CF, Input_IFRS17_Detail, dan Input_IFRS9_Detail. 3) Gunakan Mapping_Akun untuk memetakan akun audited report. 4) Review Dashboard, Rasio, CommonSize_Trend, IFRS17_Analysis, IFRS9_Analysis, Auto_Analysis, dan Validasi.
A9: Prinsip desain | B9: Template menggunakan akun standar lintas perusahaan, bukan nama akun spesifik emiten. Pos yang tidak ada boleh dibiarkan kosong. Baris opsional tersedia untuk variasi penyajian antar perusahaan.
A11: IFRS 17 – fokus utama | B11: Insurance revenue, gross claims incurred, reinsurance recoveries, acquisition cost amortisation, underwriting expenses, onerous result, LRC, LIC, outstanding claims reserve, IBNR, risk adjustment, retention ratio, dan combined ratio.
A13: IFRS 9 – fokus utama | B13: Klasifikasi FVTPL/FVOCI/Amortised Cost, ECL Stage 1–3, coverage, cadangan FVOCI, fair value movement, dan yield investasi.
A15: Keluaran otomatis | B15: Rasio profitabilitas, leverage, likuiditas, loss ratio, expense ratio, combined ratio, retention ratio, reserve leverage, common size, trend 3 tahun, analisis IFRS 17, analisis IFRS 9, validasi konsistensi, executive summary otomatis, dan dashboard ringkas.
A17: Catatan penting | B17: Template ini adalah alat analisis otomatis. Untuk keputusan profesional, tetap kombinasikan dengan pembacaan catatan atas laporan keuangan, RBC/solvency disclosure regulator, kecukupan cadangan, kualitas reasuransi, dan strategi distribusi.
A19: Definisi 'berlaku untuk seluruh asuransi jiwa' | B19: Artinya format input dan analisis ini dirancang generik untuk hampir seluruh audited report asuransi umum yang memakai IFRS 9/17; namun user tetap perlu memetakan akun audited report ke akun template karena detail disclosure tiap perusahaan dapat berbeda.
A21: Sel yang diisi user | B21: Semua sel kuning adalah input user/hardcode.
A23: Sel formula | B23: Semua sel putih berisi formula dan tidak perlu diubah.

Sheet Setup
A1: SETUP, PARAMETER, DAN BENCHMARK
A2: Parameter | B2: Nilai
A3: Nama perusahaan | B3: <isi nama perusahaan>
A4: Mata uang / unit | B4: IDR (jutaan / miliar sesuai audited report)
A5: Tahun berjalan | B5: 2025
A6: Tahun pembanding 1 | B6: 2024
A7: Tahun pembanding 2 | B7: 2023
A8: Jenis entitas | B8: Konvensional / syariah / campuran
A9: Lini utama | B9: Asuransi umum
A10: Basis standar | B10: IFRS 9 / PSAK 109 dan IFRS 17 / PSAK 117
A11: Catatan user | B11: Ubah hanya sel kuning
A13: LIKUIDITAS minimum | B13: 0.08
A14: LEVERAGE max (Liabilities/Equity) | B14: 5
A15: ROA minimum | B15: 0.01
A16: ROE minimum | B16: 0.08
A17: Net loss ratio maksimum | B17: 0.75
A18: Expense ratio maksimum | B18: 0.35
A19: Combined ratio maksimum | B19: 1
A20: Retention ratio minimum | B20: 0.5
A21: ECL coverage minimum | B21: 0.005
A22: Stage 2+3 exposure maksimum | B22: 0.15
A23: OCF / Profit minimum | B23: 0.8
A24: Reserve leverage maksimum | B24: 3

Sheet Input_SFP
A1: INPUT STATEMENT OF FINANCIAL POSITION / LAPORAN POSISI KEUANGAN
A2: Kelompok | B2: Akun standar IFRS 9 / IFRS 17 | C2: Tahun berjalan | D2: Pembanding 1 | E2: Pembanding 2 | F2: Growth vs PY | G2: Common size CY | H2: Wajib / Opsional | I2: Catatan user
A3: ASET | B3: Kas dan setara kas | F3: =IFERROR((C3/D3)-1,"") | G3: =IFERROR(C3/$C$18,"") | H3: Penting
A4: ASET | B4: Penempatan jangka pendek / pasar uang | F4: =IFERROR((C4/D4)-1,"") | G4: =IFERROR(C4/$C$18,"") | H4: Opsional
A5: ASET | B5: Investasi pada FVTPL | F5: =IFERROR((C5/D5)-1,"") | G5: =IFERROR(C5/$C$18,"") | H5: Penting
A6: ASET | B6: Investasi utang pada FVOCI | F6: =IFERROR((C6/D6)-1,"") | G6: =IFERROR(C6/$C$18,"") | H6: Penting
A7: ASET | B7: Investasi ekuitas pada FVOCI | F7: =IFERROR((C7/D7)-1,"") | G7: =IFERROR(C7/$C$18,"") | H7: Opsional
A8: ASET | B8: Investasi pada biaya perolehan diamortisasi | F8: =IFERROR((C8/D8)-1,"") | G8: =IFERROR(C8/$C$18,"") | H8: Penting
A9: ASET | B9: Properti investasi | F9: =IFERROR((C9/D9)-1,"") | G9: =IFERROR(C9/$C$18,"") | H9: Opsional
A10: ASET | B10: Piutang premi, piutang klaim, piutang reasuransi, dan piutang lain-lain | F10: =IFERROR((C10/D10)-1,"") | G10: =IFERROR(C10/$C$18,"") | H10: Opsional
A11: ASET | B11: Aset klaim / salvage / subrogasi dan aset lain-lain underwriting | F11: =IFERROR((C11/D11)-1,"") | G11: =IFERROR(C11/$C$18,"") | H11: Penting
A12: ASET | B12: Aset kontrak reasuransi | F12: =IFERROR((C12/D12)-1,"") | G12: =IFERROR(C12/$C$18,"") | H12: Penting
A13: ASET | B13: Aset akuisisi asuransi / acquisition cash flow asset | F13: =IFERROR((C13/D13)-1,"") | G13: =IFERROR(C13/$C$18,"") | H13: Opsional
A14: ASET | B14: Aset tetap, ROU, dan properti yang digunakan sendiri | F14: =IFERROR((C14/D14)-1,"") | G14: =IFERROR(C14/$C$18,"") | H14: Opsional
... A17: ASET | B17: Aset lain-lain | F17: =IFERROR((C17/D17)-1,"") | G17: =IFERROR(C17/$C$18,"") | H17: Opsional
A18: ASET | B18: TOTAL ASET | C18: =SUM(C3:C17) -> 0 | D18: =SUM(D3:D17) -> 0 | E18: =SUM(E3:E17) -> 0 | F18: =IFERROR((C18/D18)-1,"") | G18: =IFERROR(C18/$C$18,"") | H18: Formula
A19: LIABILITAS | B19: Liabilitas kontrak asuransi | F19: =IFERROR((C19/D19)-1,"") | G19: =IFERROR(C19/$C$18,"") | H19: Penting
A20: LIABILITAS | B20: Liabilitas kontrak reasuransi | F20: =IFERROR((C20/D20)-1,"") | G20: =IFERROR(C20/$C$18,"") | H20: Opsional
A21: LIABILITAS | B21: Liabilitas komponen investasi / deposit component liabilities | F21: =IFERROR((C21/D21)-1,"") | G21: =IFERROR(C21/$C$18,"") | H21: Opsional
A22: LIABILITAS | B22: Utang klaim, utang reasuransi, utang komisi, dan utang broker | F22: =IFERROR((C22/D22)-1,"") | G22: =IFERROR(C22/$C$18,"") | H22: Penting
A23: LIABILITAS | B23: Utang pajak kini/deferred tax liability | F23: =IFERROR((C23/D23)-1,"") | G23: =IFERROR(C23/$C$18,"") | H23: Opsional
A24: LIABILITAS | B24: Liabilitas sewa dan pinjaman | F24: =IFERROR((C24/D24)-1,"") | G24: =IFERROR(C24/$C$18,"") | H24: Opsional
A25: LIABILITAS | B25: Liabilitas lain-lain | F25: =IFERROR((C25/D25)-1,"") | G25: =IFERROR(C25/$C$18,"") | H25: Opsional
A26: LIABILITAS | B26: TOTAL LIABILITAS | C26: =SUM(C19:C25) -> 0 | D26: =SUM(D19:D25) -> 0 | E26: =SUM(E19:E25) -> 0 | F26: =IFERROR((C26/D26)-1,"") | G26: =IFERROR(C26/$C$18,"") | H26: Formula
A27: DANA PESERTA | B27: Dana tabarru / dana peserta (opsional untuk syariah) | F27: =IFERROR((C27/D27)-1,"") | G27: =IFERROR(C27/$C$18,"") | H27: Opsional
A28: EKUITAS | B28: Modal saham | F28: =IFERROR((C28/D28)-1,"") | G28: =IFERROR(C28/$C$18,"") | H28: Penting
A29: EKUITAS | B29: Tambahan modal disetor | F29: =IFERROR((C29/D29)-1,"") | G29: =IFERROR(C29/$C$18,"") | H29: Opsional
A30: EKUITAS | B30: Saldo laba | F30: =IFERROR((C30/D30)-1,"") | G30: =IFERROR(C30/$C$18,"") | H30: Penting
A31: EKUITAS | B31: Cadangan FVOCI / fair value reserve | F31: =IFERROR((C31/D31)-1,"") | G31: =IFERROR(C31/$C$18,"") | H31: Penting
A32: EKUITAS | B32: Cadangan insurance finance OCI | F32: =IFERROR((C32/D32)-1,"") | G32: =IFERROR(C32/$C$18,"") | H32: Opsional
A33: EKUITAS | B33: Cadangan OCI dan cadangan lain-lain | F33: =IFERROR((C33/D33)-1,"") | G33: =IFERROR(C33/$C$18,"") | H33: Opsional
A34: EKUITAS | B34: TOTAL EKUITAS | C34: =SUM(C28:C33) -> 0 | D34: =SUM(D28:D33) -> 0 | E34: =SUM(E28:E33) -> 0 | F34: =IFERROR((C34/D34)-1,"") | G34: =IFERROR(C34/$C$18,"") | H34: Formula
A35: KONTROL | B35: TOTAL LIAB + DANA PESERTA + EKUITAS | C35: =C26+C27+C34 -> 0 | D35: =D26+D27+D34 -> 0 | E35: =E26+E27+E34 -> 0 | F35: =IFERROR((C35/D35)-1,"") | G35: =IFERROR(C35/$C$18,"") | H35: Formula

Sheet Input_PL_OCI
A1: INPUT PROFIT OR LOSS & OTHER COMPREHENSIVE INCOME – ASURANSI UMUM
A2: Kelompok | B2: Akun standar | C2: Tahun berjalan | D2: Pembanding 1 | E2: Pembanding 2 | F2: Growth vs PY | G2: Margin / Ratio CY | H2: Wajib / Opsional | I2: Catatan user
A3: HASIL JASA ASURANSI | B3: Insurance revenue | F3: =IFERROR((C3/D3)-1,"") | G3: =IFERROR(C3/C3,"") | H3: Penting
A4: HASIL JASA ASURANSI | B4: Insurance service expense (claims + attributable expenses) | F4: =IFERROR((C4/D4)-1,"") | G4: =IFERROR(C4/C3,"") | H4: Penting
A5: HASIL JASA ASURANSI | B5: Net expense/(income) from reinsurance/retrocession contracts held | F5: =IFERROR((C5/D5)-1,"") | G5: =IFERROR(C5/C3,"") | H5: Penting
A6: HASIL JASA ASURANSI | B6: INSURANCE SERVICE RESULT | C6: =SUM(C3:C5) -> 0 | D6: =SUM(D3:D5) -> 0 | E6: =SUM(E3:E5) -> 0 | F6: =IFERROR((C6/D6)-1,"") | G6: =IFERROR(C6/C3,"") | H6: Formula
A7: INVESTASI & KEUANGAN | B7: Net investment result / investment income - net | F7: =IFERROR((C7/D7)-1,"") | G7: =IFERROR(C7/C22,"") | H7: Penting
A8: INVESTASI & KEUANGAN | B8: Insurance finance income/(expense) from contracts issued | F8: =IFERROR((C8/D8)-1,"") | G8: =IFERROR(C8/C22,"") | H8: Opsional
A9: INVESTASI & KEUANGAN | B9: Insurance finance income/(expense) from reinsurance held | F9: =IFERROR((C9/D9)-1,"") | G9: =IFERROR(C9/C22,"") | H9: Opsional
A10: INVESTASI & KEUANGAN | B10: Net impairment gain/(loss) on financial assets | F10: =IFERROR((C10/D10)-1,"") | G10: =IFERROR(C10/C22,"") | H10: Opsional
A11: INVESTASI & KEUANGAN | B11: Fee, brokerage, and other operating income | F11: =IFERROR((C11/D11)-1,"") | G11: =IFERROR(C11/C22,"") | H11: Opsional
A12: BEBAN | B12: Operating expenses outside insurance service expense | F12: =IFERROR((C12/D12)-1,"") | G12: =IFERROR(C12/C22,"") | H12: Penting
A13: BEBAN | B13: Finance costs and other non-operating items | F13: =IFERROR((C13/D13)-1,"") | G13: =IFERROR(C13/C22,"") | H13: Opsional
A14: LABA | B14: PROFIT BEFORE TAX | C14: =SUM(C6:C13) -> 0 | D14: =SUM(D6:D13) -> 0 | E14: =SUM(E6:E13) -> 0 | F14: =IFERROR((C14/D14)-1,"") | G14: =IFERROR(C14/C22,"") | H14: Formula
A15: LABA | B15: Income tax expense | F15: =IFERROR((C15/D15)-1,"") | G15: =IFERROR(C15/C22,"") | H15: Penting
A16: LABA | B16: PROFIT FOR THE YEAR | C16: =SUM(C14:C15) -> 0 | D16: =SUM(D14:D15) -> 0 | E16: =SUM(E14:E15) -> 0 | F16: =IFERROR((C16/D16)-1,"") | G16: =IFERROR(C16/C22,"") | H16: Formula
A17: OCI | B17: OCI - FVOCI reserve movement | F17: =IFERROR((C17/D17)-1,"") | G17: =IFERROR(C17/C22,"") | H17: Opsional
A18: OCI | B18: OCI - insurance finance OCI | F18: =IFERROR((C18/D18)-1,"") | G18: =IFERROR(C18/C22,"") | H18: Opsional
A19: OCI | B19: OCI - other OCI | F19: =IFERROR((C19/D19)-1,"") | G19: =IFERROR(C19/C22,"") | H19: Opsional
A20: OCI | B20: TOTAL OCI | C20: =SUM(C17:C19) -> 0 | D20: =SUM(D17:D19) -> 0 | E20: =SUM(E17:E19) -> 0 | F20: =IFERROR((C20/D20)-1,"") | G20: =IFERROR(C20/C22,"") | H20: Formula
A21: OCI | B21: TOTAL COMPREHENSIVE INCOME | C21: =C16+C20 -> 0 | D21: =D16+D20 -> 0 | E21: =E16+E20 -> 0 | F21: =IFERROR((C21/D21)-1,"") | G21: =IFERROR(C21/C22,"") | H21: Formula
A22: KONTROL | B22: TOTAL INCOME (MANAGEMENT VIEW) | C22: =SUM(C3,C7:C11) -> 0 | D22: =SUM(D3,D7:D11) -> 0 | E22: =SUM(E3,E7:E11) -> 0 | F22: =IFERROR((C22/D22)-1,"") | G22: =IFERROR(C22/C22,"") | H22: Formula

Sheet Input_CF
A1: INPUT STATEMENT OF CASH FLOWS
A2: Kelompok | B2: Akun | C2: Tahun berjalan | D2: Pembanding 1 | E2: Pembanding 2 | F2: Growth vs PY | G2: Ratio CY | H2: Catatan
A3: OPERASI | B3: Net cash from/(used in) operating activities | F3: =IFERROR((C3/D3)-1,"") | G3: =IFERROR(C3/Input_PL_OCI!C16,"")
A4: INVESTASI | B4: Net cash from/(used in) investing activities | F4: =IFERROR((C4/D4)-1,"") | G4: =IFERROR(C4/Input_PL_OCI!C16,"")
A5: PENDANAAN | B5: Net cash from/(used in) financing activities | F5: =IFERROR((C5/D5)-1,"") | G5: =IFERROR(C5/Input_PL_OCI!C16,"")
A6: NETO | B6: Net increase/(decrease) in cash | C6: =SUM(C3:C5) -> 0 | D6: =SUM(D3:D5) -> 0 | E6: =SUM(E3:E5) -> 0 | F6: =IFERROR((C6/D6)-1,"") | G6: =IFERROR(C6/Input_PL_OCI!C16,"")
A7: SALDO | B7: Cash and cash equivalents at beginning of year | F7: =IFERROR((C7/D7)-1,"") | G7: =IFERROR(C7/Input_PL_OCI!C16,"")
A8: SALDO | B8: Cash and cash equivalents at end of year | C8: =C7+C6 -> 0 | D8: =D7+D6 -> 0 | E8: =E7+E6 -> 0 | F8: =IFERROR((C8/D8)-1,"") | G8: =IFERROR(C8/Input_PL_OCI!C16,"")

Sheet Input_IFRS17_Detail
A1: INPUT DETAIL IFRS 17 / PSAK 117 – ASURANSI UMUM
A2: Blok | B2: Metrik | C2: Tahun berjalan | D2: Pembanding 1 | E2: Pembanding 2 | F2: Growth vs PY | G2: Fokus / rasio | H2: Portofolio / kelompok | I2: Wajib / Opsional | J2: Catatan user
A3: Hasil jasa | B3: Insurance revenue total | F3: =IFERROR((C3/D3)-1,"") | G3: Skala | I3: Penting
A4: Hasil jasa | B4: Gross claims incurred | F4: =IFERROR((C4/D4)-1,"") | G4: Klaim bruto | I4: Penting
A5: Hasil jasa | B5: Reinsurance recoveries / gains related to claims (input positif bila memulihkan klaim) | F5: =IFERROR((C5/D5)-1,"") | G5: Proteksi reasuransi | I5: Penting
A6: Hasil jasa | B6: Acquisition cash flow amortisation / commissions in service expense | F6: =IFERROR((C6/D6)-1,"") | G6: Akuisisi | I6: Penting
A7: Hasil jasa | B7: Other directly attributable underwriting expenses | F7: =IFERROR((C7/D7)-1,"") | G7: Biaya underwriting | I7: Penting
A8: Hasil jasa | B8: Losses on onerous contracts and reversals | F8: =IFERROR((C8/D8)-1,"") | G8: Onerous | I8: Opsional
A9: Hasil jasa | B9: INSURANCE SERVICE RESULT | C9: =SUM(C3:C8) -> 0 | D9: =SUM(D3:D8) -> 0 | E9: =SUM(E3:E8) -> 0 | F9: =IFERROR((C9/D9)-1,"") | G9: Margin | I9: Formula
A10: Keuangan | B10: Insurance finance income/(expense) - contracts issued | F10: =IFERROR((C10/D10)-1,"") | G10: Volatilitas | I10: Opsional
A11: Keuangan | B11: Insurance finance income/(expense) - reinsurance held | F11: =IFERROR((C11/D11)-1,"") | G11: Offset | I11: Opsional
A12: Keuangan | B12: INSURANCE RESULT AFTER FINANCE | C12: =C9+SUM(C10:C11) -> 0 | D12: =D9+SUM(D10:D11) -> 0 | E12: =E9+SUM(E10:E11) -> 0 | F12: =IFERROR((C12/D12)-1,"") | G12: Result | I12: Formula
A13: Posisi keuangan | B13: Insurance contract liabilities | F13: =IFERROR((C13/D13)-1,"") | G13: Kewajiban | I13: Penting
A14: Posisi keuangan | B14: Reinsurance contract assets | F14: =IFERROR((C14/D14)-1,"") | G14: Aset reasuransi | I14: Penting
A15: Posisi keuangan | B15: Reinsurance contract liabilities | F15: =IFERROR((C15/D15)-1,"") | G15: Liabilitas reasuransi | I15: Opsional
A16: Posisi keuangan | B16: Liability for remaining coverage (LRC) excl. loss component | F16: =IFERROR((C16/D16)-1,"") | G16: LRC | I16: Penting
A17: Posisi keuangan | B17: Liability for incurred claims (LIC) | F17: =IFERROR((C17/D17)-1,"") | G17: LIC | I17: Penting
A18: Posisi keuangan | B18: Loss component | F18: =IFERROR((C18/D18)-1,"") | G18: Onerous | I18: Opsional
A19: Posisi keuangan | B19: Risk adjustment for non-financial risk | F19: =IFERROR((C19/D19)-1,"") | G19: RA | I19: Penting
A20: Cadangan | B20: Outstanding claims reserve / case reserve | F20: =IFERROR((C20/D20)-1,"") | G20: OCR | I20: Penting
A21: Cadangan | B21: IBNR reserve | F21: =IFERROR((C21/D21)-1,"") | G21: IBNR | I21: Penting
A22: Aset terkait | B22: Acquisition cash flow asset / DAC (jika disajikan terpisah) | F22: =IFERROR((C22/D22)-1,"") | G22: DAC | I22: Opsional
A23: Reasuransi | B23: Ceded share of reserves / reinsurance recoverables on LIC | F23: =IFERROR((C23/D23)-1,"") | G23: Proteksi cadangan | I23: Opsional
A24: Manajemen | B24: Gross written premium / GWP equivalent (management metric) | F24: =IFERROR((C24/D24)-1,"") | G24: Skala bruto | I24: Opsional
A25: Manajemen | B25: Net written premium / NWP equivalent (management metric) | F25: =IFERROR((C25/D25)-1,"") | G25: Skala neto | I25: Opsional
A26: Rasio bantu | B26: Retention ratio | C26: =IFERROR(C25/C24,"") | D26: =IFERROR(D25/D24,"") | E26: =IFERROR(E25/E24,"") | F26: =IFERROR((C26/D26)-1,"") | G26: Retensi | I26: Formula
A27: Rasio bantu | B27: Underwriting expenses total | C27: =SUM(C6:C8) -> 0 | D27: =SUM(D6:D8) -> 0 | E27: =SUM(E6:E8) -> 0 | F27: =IFERROR((C27/D27)-1,"") | G27: Biaya underwriting | I27: Formula
A28: Rasio bantu | B28: Net loss ratio | C28: =IFERROR(ABS((C4-C5)/C3),"") | D28: =IFERROR(ABS((D4-D5)/D3),"") | E28: =IFERROR(ABS((E4-E5)/E3),"") | F28: =IFERROR((C28/D28)-1,"") | G28: Klaim neto | I28: Formula
A29: Rasio bantu | B29: Expense ratio | C29: =IFERROR(ABS(C27/C3),"") | D29: =IFERROR(ABS(D27/D3),"") | E29: =IFERROR(ABS(E27/E3),"") | F29: =IFERROR((C29/D29)-1,"") | G29: Efisiensi | I29: Formula
A30: Rasio bantu | B30: Combined ratio | C30: =IFERROR(C28+C29,"") | D30: =IFERROR(D28+D29,"") | E30: =IFERROR(E28+E29,"") | F30: =IFERROR((C30/D30)-1,"") | G30: Profit underwriting | I30: Formula
A31: Rasio bantu | B31: Reserve leverage | C31: =IFERROR((C20+C21)/Input_SFP!C34,"") | D31: =IFERROR((D20+D21)/Input_SFP!D34,"") | E31: =IFERROR((E20+E21)/Input_SFP!E34,"") | F31: =IFERROR((C31/D31)-1,"") | G31: Cadangan vs ekuitas | I31: Formula
A32: Rasio bantu | B32: Reinsurance asset / equity | C32: =IFERROR(C14/Input_SFP!C34,"") | D32: =IFERROR(D14/Input_SFP!D34,"") | E32: =IFERROR(E14/Input_SFP!E34,"") | F32: =IFERROR((C32/D32)-1,"") | G32: Ketergantungan reasuransi | I32: Formula

Sheet Input_IFRS9_Detail
A1: INPUT DETAIL IFRS 9 / PSAK 109
A2: Blok | B2: Metrik | C2: Tahun berjalan | D2: Pembanding 1 | E2: Pembanding 2 | F2: Growth vs PY | G2: Klasifikasi | H2: Stage | I2: Wajib / Opsional | J2: Catatan user | K2: Coverage / Ratio
A3: Aset keuangan | B3: FVTPL carrying amount | F3: =IFERROR((C3/D3)-1,"") | G3: FVTPL | I3: Opsional
A4: Aset keuangan | B4: FVOCI debt instruments carrying amount | F4: =IFERROR((C4/D4)-1,"") | G4: FVOCI | I4: Penting
A5: Aset keuangan | B5: FVOCI equity instruments carrying amount | F5: =IFERROR((C5/D5)-1,"") | G5: FVOCI | I5: Opsional
A6: Aset keuangan | B6: Amortised cost debt instruments carrying amount | F6: =IFERROR((C6/D6)-1,"") | G6: AC | I6: Penting
A7: Aset keuangan | B7: Loans and receivables carrying amount | F7: =IFERROR((C7/D7)-1,"") | G7: AC | I7: Opsional
A8: ECL | B8: TOTAL financial assets subject to ECL | C8: =SUM(C4,C6,C7) -> 0 | D8: =SUM(D4,D6,D7) -> 0 | E8: =SUM(E4,E6,E7) -> 0 | F8: =IFERROR((C8/D8)-1,"") | G8: AC/FVOCI | I8: Formula
A9: ECL | B9: Stage 1 gross exposure | F9: =IFERROR((C9/D9)-1,"") | G9: AC/FVOCI | H9: Stage 1 | I9: Penting
A10: ECL | B10: Stage 2 gross exposure | F10: =IFERROR((C10/D10)-1,"") | G10: AC/FVOCI | H10: Stage 2 | I10: Penting
A11: ECL | B11: Stage 3 gross exposure | F11: =IFERROR((C11/D11)-1,"") | G11: AC/FVOCI | H11: Stage 3 | I11: Penting
A12: ECL | B12: Stage 1 allowance | F12: =IFERROR((C12/D12)-1,"") | G12: AC/FVOCI | H12: Stage 1 | I12: Penting
A13: ECL | B13: Stage 2 allowance | F13: =IFERROR((C13/D13)-1,"") | G13: AC/FVOCI | H13: Stage 2 | I13: Penting
A14: ECL | B14: Stage 3 allowance | F14: =IFERROR((C14/D14)-1,"") | G14: AC/FVOCI | H14: Stage 3 | I14: Penting
A15: ECL | B15: TOTAL allowance ECL | C15: =SUM(C12:C14) -> 0 | D15: =SUM(D12:D14) -> 0 | E15: =SUM(E12:E14) -> 0 | F15: =IFERROR((C15/D15)-1,"") | G15: AC/FVOCI | H15: All | I15: Formula
A16: ECL | B16: Coverage on ECL assets | C16: =IFERROR(C15/C8,"") | D16: =IFERROR(D15/D8,"") | E16: =IFERROR(E15/E8,"") | F16: =IFERROR((C16/D16)-1,"") | G16: AC/FVOCI | I16: Formula
A17: Kualitas aset | B17: Low credit risk exposure | F17: =IFERROR((C17/D17)-1,"") | G17: AC/FVOCI | I17: Opsional
A18: Kualitas aset | B18: Credit-impaired exposure | F18: =IFERROR((C18/D18)-1,"") | G18: AC/FVOCI | I18: Penting
A19: Kualitas aset | B19: Write-offs during year | F19: =IFERROR((C19/D19)-1,"") | G19: AC/FVOCI | I19: Opsional
A20: Kualitas aset | B20: Recovery of written-off assets | F20: =IFERROR((C20/D20)-1,"") | G20: AC/FVOCI | I20: Opsional
A21: OCI | B21: FVOCI reserve closing | F21: =IFERROR((C21/D21)-1,"") | G21: FVOCI | I21: Penting
A22: P/L | B22: Fair value gain/(loss) on FVTPL recognised in P/L | F22: =IFERROR((C22/D22)-1,"") | G22: FVTPL | I22: Opsional
A23: P/L | B23: Investment income on financial assets | F23: =IFERROR((C23/D23)-1,"") | G23: All | I23: Penting
A24: P/L | B24: Average investment assets | F24: =IFERROR((C24/D24)-1,"") | G24: All | I24: Opsional
A25: P/L | B25: Portfolio yield | C25: =IFERROR(C23/C24,"") | D25: =IFERROR(D23/D24,"") | E25: =IFERROR(E23/E24,"") | F25: =IFERROR((C25/D25)-1,"") | G25: All | I25: Formula
A26: Sensitivitas | B26: Interest rate duration / sensitivity (years) | F26: =IFERROR((C26/D26)-1,"") | G26: All | I26: Opsional

Sheet Mapping_Akun
A1: MAPPING AKUN STANDAR IFRS 9 / IFRS 17 UNTUK AUDITED REPORT ASURANSI UMUM
A2: Kelompok | B2: Akun standar template | C2: Contoh nama akun pada audited report | D2: Standar utama | E2: Sheet input | F2: Wajib / Opsional | G2: Catatan
A3: SFP | B3: Aset kontrak reasuransi | C3: Reinsurance contract assets / aset reasuransi | D3: IFRS 17 | E3: Input_SFP | F3: Penting | G3: Posisi neraca reasuransi ceded
A4: SFP | B4: Liabilitas kontrak asuransi | C4: Insurance contract liabilities / liabilitas kontrak asuransi | D4: IFRS 17 | E4: Input_SFP | F4: Penting | G4: Kewajiban utama pasca IFRS 17
A5: SFP | B5: Utang klaim, utang reasuransi, utang komisi, dan utang broker | C5: Claims payable / reinsurance payable / commission payable | D5: IFRS 17 | E5: Input_SFP | F5: Penting | G5: Kewajiban underwriting lain
A6: PL | B6: Insurance revenue | C6: Pendapatan asuransi | D6: IFRS 17 | E6: Input_PL_OCI | F6: Penting | G6: Bukan premi bruto IFRS 4
A7: PL | B7: Insurance service expense | C7: Beban jasa asuransi | D7: IFRS 17 | E7: Input_PL_OCI | F7: Penting | G7: Klaim dan biaya langsung
A8: PL | B8: Net expense/(income) from reinsurance contracts held | C8: Beban/(pendapatan) bersih reasuransi | D8: IFRS 17 | E8: Input_PL_OCI | F8: Penting | G8: Offset proteksi reasuransi
A9: IFRS17 | B9: Gross claims incurred | C9: Klaim bruto terjadi / incurred claims | D9: IFRS 17 | E9: Input_IFRS17_Detail | F9: Penting | G9: Dasar loss ratio
A10: IFRS17 | B10: Reinsurance recoveries related to claims | C10: Pemulihan reasuransi atas klaim | D10: IFRS 17 | E10: Input_IFRS17_Detail | F10: Penting | G10: Input positif bila mengurangi klaim neto
A11: IFRS17 | B11: LRC / LIC / OCR / IBNR | C11: LRC, LIC, outstanding claims reserve, IBNR | D11: IFRS 17 | E11: Input_IFRS17_Detail | F11: Penting | G11: Cadangan utama asuransi umum
A12: IFRS17 | B12: Gross written premium / Net written premium equivalent | C12: GWP / NWP management metric | D12: Management | E12: Input_IFRS17_Detail | F12: Opsional | G12: Mempermudah retention ratio
A13: IFRS9 | B13: Stage 1/2/3 exposures & allowances | C13: Eksposur ECL per stage dan allowance | D13: IFRS 9 | E13: Input_IFRS9_Detail | F13: Penting | G13: Dasar analisis kualitas kredit
A14: IFRS9 | B14: FVOCI reserve closing | C14: Cadangan FVOCI / fair value reserve | D14: IFRS 9 | E14: Input_IFRS9_Detail | F14: Penting | G14: Sensitivitas OCI

Sheet Rasio
A1: RASIO KEUANGAN OTOMATIS – KHUSUS ASURANSI UMUM
A2: Kategori | B2: Rasio | C2: Rumus | D2: CY | E2: PY | F2: PPY | G2: Interpretasi otomatis | H2: Catatan
A3: Profitabilitas | B3: ROA | C3: Profit for the year / Total assets | D3: =IFERROR(Input_PL_OCI!C16/Input_SFP!C18,"") | E3: =IFERROR(Input_PL_OCI!D16/Input_SFP!D18,"") | F3: =IFERROR(Input_PL_OCI!E16/Input_SFP!E18,"") | G3: =IF(D3>=Setup!$B$15,"Sehat","Perlu perhatian") -> Sehat
A4: Profitabilitas | B4: ROE | C4: Profit for the year / Total equity | D4: =IFERROR(Input_PL_OCI!C16/Input_SFP!C34,"") | E4: =IFERROR(Input_PL_OCI!D16/Input_SFP!D34,"") | F4: =IFERROR(Input_PL_OCI!E16/Input_SFP!E34,"") | G4: =IF(D4>=Setup!$B$16,"Sehat","Perlu perhatian") -> Sehat
A5: Underwriting | B5: Net loss ratio | C5: Net claims / insurance revenue | D5: =IFERROR(Input_IFRS17_Detail!C28,"") | E5: =IFERROR(Input_IFRS17_Detail!D28,"") | F5: =IFERROR(Input_IFRS17_Detail!E28,"") | G5: =IF(D5<=Setup!$B$17,"Terkendali","Tinggi") -> Tinggi
A6: Underwriting | B6: Expense ratio | C6: Underwriting expenses / insurance revenue | D6: =IFERROR(Input_IFRS17_Detail!C29,"") | E6: =IFERROR(Input_IFRS17_Detail!D29,"") | F6: =IFERROR(Input_IFRS17_Detail!E29,"") | G6: =IF(D6<=Setup!$B$18,"Efisien","Beban tinggi") -> Beban tinggi
A7: Underwriting | B7: Combined ratio | C7: Net loss ratio + expense ratio | D7: =IFERROR(Input_IFRS17_Detail!C30,"") | E7: =IFERROR(Input_IFRS17_Detail!D30,"") | F7: =IFERROR(Input_IFRS17_Detail!E30,"") | G7: =IF(D7<=Setup!$B$19,"Underwriting positif","Underwriting tertekan") -> Underwriting tertekan
A8: Reasuransi | B8: Retention ratio | C8: NWP/GWP equivalent | D8: =IFERROR(Input_IFRS17_Detail!C26,"") | E8: =IFERROR(Input_IFRS17_Detail!D26,"") | F8: =IFERROR(Input_IFRS17_Detail!E26,"") | G8: =IF(D8>=Setup!$B$20,"Retensi memadai","Ketergantungan reasuransi tinggi") -> Retensi memadai
A9: Cadangan | B9: Reserve leverage | C9: (OCR+IBNR) / equity | D9: =IFERROR(Input_IFRS17_Detail!C31,"") | E9: =IFERROR(Input_IFRS17_Detail!D31,"") | F9: =IFERROR(Input_IFRS17_Detail!E31,"") | G9: =IF(D9<=Setup!$B$24,"Cadangan vs modal terkendali","Cadangan tinggi vs ekuitas") -> Cadangan tinggi vs ekuitas
A10: Reasuransi | B10: Reinsurance asset / Equity | C10: Reinsurance contract assets / equity | D10: =IFERROR(Input_IFRS17_Detail!C32,"") | E10: =IFERROR(Input_IFRS17_Detail!D32,"") | F10: =IFERROR(Input_IFRS17_Detail!E32,"") | G10: =IF(D10<=1,"Eksposur reasuransi masih terkendali","Ketergantungan reasuransi besar") -> Ketergantungan reasuransi besar
A11: Leverage | B11: Liabilities / Equity | C11: Total liabilities / Total equity | D11: =IFERROR(Input_SFP!C26/Input_SFP!C34,"") | E11: =IFERROR(Input_SFP!D26/Input_SFP!D34,"") | F11: =IFERROR(Input_SFP!E26/Input_SFP!E34,"") | G11: =IF(D11<=Setup!$B$14,"Terkendali","Tinggi") -> Tinggi
A12: Likuiditas | B12: Cash / Liabilities | C12: Cash & equivalents / Total liabilities | D12: =IFERROR(Input_SFP!C3/Input_SFP!C26,"") | E12: =IFERROR(Input_SFP!D3/Input_SFP!D26,"") | F12: =IFERROR(Input_SFP!E3/Input_SFP!E26,"") | G12: =IF(D12>=Setup!$B$13,"Likuiditas awal memadai","Perlu review likuiditas") -> Likuiditas awal memadai
A13: IFRS 9 | B13: ECL coverage | C13: Total allowance / Financial assets subject to ECL | D13: =IFERROR(Input_IFRS9_Detail!C15/Input_IFRS9_Detail!C8,"") | E13: =IFERROR(Input_IFRS9_Detail!D15/Input_IFRS9_Detail!D8,"") | F13: =IFERROR(Input_IFRS9_Detail!E15/Input_IFRS9_Detail!E8,"") | G13: =IF(D13>=Setup!$B$21,"Coverage memadai","Coverage tipis / belum lengkap") -> Coverage memadai
A14: IFRS 9 | B14: Stage 2+3 ratio | C14: (Stage 2 + Stage 3 exposure) / total ECL assets | D14: =IFERROR((Input_IFRS9_Detail!C10+Input_IFRS9_Detail!C11)/Input_IFRS9_Detail!C8,"") | E14: =IFERROR((Input_IFRS9_Detail!D10+Input_IFRS9_Detail!D11)/Input_IFRS9_Detail!D8,"") | F14: =IFERROR((Input_IFRS9_Detail!E10+Input_IFRS9_Detail!E11)/Input_IFRS9_Detail!E8,"") | G14: =IF(D14<=Setup!$B$22,"Kualitas kredit relatif baik","Migrasi kredit meningkat") -> Migrasi kredit meningkat
A15: Arus kas | B15: OCF / Profit | C15: Operating cash flow / Profit | D15: =IFERROR(Input_CF!C3/Input_PL_OCI!C16,"") | E15: =IFERROR(Input_CF!D3/Input_PL_OCI!D16,"") | F15: =IFERROR(Input_CF!E3/Input_PL_OCI!E16,"") | G15: =IF(D15>=Setup!$B$23,"Konversi laba ke kas baik","Kas operasi lemah vs laba") -> Konversi laba ke kas baik
A16: Arus kas | B16: Ending cash vs SFP cash | C16: Cash ending CF / Cash SFP | D16: =IFERROR(Input_CF!C8/Input_SFP!C3,"") | E16: =IFERROR(Input_CF!D8/Input_SFP!D3,"") | F16: =IFERROR(Input_CF!E8/Input_SFP!E3,"") | G16: =IF(ABS(D16-1)<0.02,"Konsisten","Perlu rekonsiliasi") -> #VALUE!

Sheet CommonSize_Trend
A1: COMMON SIZE, TREND, DAN GERAKAN 3 TAHUN – ASURANSI UMUM
A2: Statement | B2: Akun | C2: CY | D2: PY | E2: PPY | F2: Common size CY | G2: Common size PY | H2: Growth CY vs PY | I2: Growth PY vs PPY | J2: Arah
A3: SFP | B3: Total assets | C3: =Input_SFP!C18 -> 0 | D3: =Input_SFP!D18 -> 0 | E3: =Input_SFP!E18 -> 0 | F3: =1 -> 1 | G3: =1 -> 1 | H3: =IFERROR((C3/D3)-1,"") | I3: =IFERROR((D3/E3)-1,"") | J3: =IF(H3>0,"Naik","Turun") -> Naik
A4: SFP | B4: Total liabilities | C4: =Input_SFP!C26 -> 0 | D4: =Input_SFP!D26 -> 0 | E4: =Input_SFP!E26 -> 0 | F4: =IFERROR(C4/C3,"") | G4: =IFERROR(D4/D3,"") | H4: =IFERROR((C4/D4)-1,"") | I4: =IFERROR((D4/E4)-1,"") | J4: =IF(H4>0,"Naik","Turun") -> Naik
A5: SFP | B5: Total equity | C5: =Input_SFP!C34 -> 0 | D5: =Input_SFP!D34 -> 0 | E5: =Input_SFP!E34 -> 0 | F5: =IFERROR(C5/C3,"") | G5: =IFERROR(D5/D3,"") | H5: =IFERROR((C5/D5)-1,"") | I5: =IFERROR((D5/E5)-1,"") | J5: =IF(H5>0,"Naik","Turun") -> Naik
A6: PL | B6: Insurance revenue | C6: =Input_PL_OCI!C3 -> 0 | D6: =Input_PL_OCI!D3 -> 0 | E6: =Input_PL_OCI!E3 -> 0 | F6: =1 -> 1 | G6: =1 -> 1 | H6: =IFERROR((C6/D6)-1,"") | I6: =IFERROR((D6/E6)-1,"") | J6: =IF(H6>0,"Naik","Turun") -> Naik
A7: PL | B7: Insurance service result | C7: =Input_PL_OCI!C6 -> 0 | D7: =Input_PL_OCI!D6 -> 0 | E7: =Input_PL_OCI!E6 -> 0 | F7: =IFERROR(C7/C6,"") | G7: =IFERROR(D7/D6,"") | H7: =IFERROR((C7/D7)-1,"") | I7: =IFERROR((D7/E7)-1,"") | J7: =IF(H7>0,"Naik","Turun") -> Naik
A8: PL | B8: Profit for the year | C8: =Input_PL_OCI!C16 -> 0 | D8: =Input_PL_OCI!D16 -> 0 | E8: =Input_PL_OCI!E16 -> 0 | F8: =IFERROR(C8/Input_PL_OCI!C22,"") | G8: =IFERROR(D8/Input_PL_OCI!D22,"") | H8: =IFERROR((C8/D8)-1,"") | I8: =IFERROR((D8/E8)-1,"") | J8: =IF(H8>0,"Naik","Turun") -> Naik
A9: IFRS17 | B9: Net loss ratio | C9: =Rasio!D5 | D9: =Rasio!E5 | E9: =Rasio!F5 | F9: =Rasio!D5 | G9: =Rasio!E5 | H9: =IFERROR((C9/D9)-1,"") | I9: =IFERROR((D9/E9)-1,"") | J9: =IF(H9>0,"Naik","Turun") -> Naik
A10: IFRS17 | B10: Combined ratio | C10: =Rasio!D7 | D10: =Rasio!E7 | E10: =Rasio!F7 | F10: =Rasio!D7 | G10: =Rasio!E7 | H10: =IFERROR((C10/D10)-1,"") | I10: =IFERROR((D10/E10)-1,"") | J10: =IF(H10>0,"Naik","Turun") -> Naik
A11: IFRS17 | B11: Reserve leverage | C11: =Rasio!D9 | D11: =Rasio!E9 | E11: =Rasio!F9 | F11: =Rasio!D9 | G11: =Rasio!E9 | H11: =IFERROR((C11/D11)-1,"") | I11: =IFERROR((D11/E11)-1,"") | J11: =IF(H11>0,"Naik","Turun") -> Naik
A12: IFRS9 | B12: Total ECL allowance | C12: =Input_IFRS9_Detail!C15 -> 0 | D12: =Input_IFRS9_Detail!D15 -> 0 | E12: =Input_IFRS9_Detail!E15 -> 0 | F12: =IFERROR(C12/Input_IFRS9_Detail!C8,"") | G12: =IFERROR(D12/Input_IFRS9_Detail!D8,"") | H12: =IFERROR((C12/D12)-1,"") | I12: =IFERROR((D12/E12)-1,"") | J12: =IF(H12>0,"Naik","Turun") -> Naik

Sheet IFRS17_Analysis
A1: ANALISIS KHUSUS IFRS 17 / PSAK 117 – ASURANSI UMUM
A2: Indikator | B2: CY | C2: PY | D2: Perubahan | E2: Interpretasi otomatis | F2: Fokus analisis | G2: Catatan
A3: Insurance revenue | B3: =Input_IFRS17_Detail!C3 -> 0 | C3: =Input_IFRS17_Detail!D3 -> 0 | D3: =IFERROR((B3/C3)-1,"") | E3: =IF(B3>0,"Pendapatan asuransi tersedia","Belum diisi") -> Belum diisi | F3: Skala bisnis
A4: Insurance service result | B4: =Input_IFRS17_Detail!C9 -> 0 | C4: =Input_IFRS17_Detail!D9 -> 0 | D4: =IFERROR((B4/C4)-1,"") | E4: =IF(B4>0,"Underwriting/service result positif","Underwriting/service result negatif") -> Underwriting/service result negatif | F4: Kualitas laba inti
A5: Net loss ratio | B5: =Rasio!D5 | C5: =Rasio!E5 | D5: =IFERROR((B5/C5)-1,"") | E5: =IF(B5<=Setup!$B$17,"Loss ratio terkendali","Loss ratio tinggi") -> Loss ratio tinggi | F5: Profit underwriting
A6: Expense ratio | B6: =Rasio!D6 | C6: =Rasio!E6 | D6: =IFERROR((B6/C6)-1,"") | E6: =IF(B6<=Setup!$B$18,"Expense ratio efisien","Expense ratio tinggi") -> Expense ratio tinggi | F6: Efisiensi
A7: Combined ratio | B7: =Rasio!D7 | C7: =Rasio!E7 | D7: =IFERROR((B7/C7)-1,"") | E7: =IF(B7<=Setup!$B$19,"Combined ratio sehat","Combined ratio > 100%") -> Combined ratio > 100% | F7: Kualitas underwriting
A8: Retention ratio | B8: =Rasio!D8 | C8: =Rasio!E8 | D8: =IFERROR((B8/C8)-1,"") | E8: =IF(B8>=Setup!$B$20,"Retensi memadai","Ketergantungan reasuransi tinggi") -> Retensi memadai | F8: Strategi proteksi
A9: Reserve leverage | B9: =Rasio!D9 | C9: =Rasio!E9 | D9: =IFERROR((B9/C9)-1,"") | E9: =IF(B9<=Setup!$B$24,"Cadangan vs modal terkendali","Cadangan berat terhadap modal") -> Cadangan berat terhadap modal | F9: Cadangan teknis
A10: Reinsurance asset / equity | B10: =Rasio!D10 | C10: =Rasio!E10 | D10: =IFERROR((B10/C10)-1,"") | E10: =IF(B10<=1,"Eksposur reasuransi moderat","Eksposur reasuransi besar") -> Eksposur reasuransi besar | F10: Counterparty dependence
A11: LIC / LRC check | B11: =IFERROR(Input_IFRS17_Detail!C17/Input_IFRS17_Detail!C16,"") | C11: =IFERROR(Input_IFRS17_Detail!D17/Input_IFRS17_Detail!D16,"") | D11: =IFERROR((B11/C11)-1,"") | E11: =IF(B11>1,"LIC > LRC","LRC >= LIC atau data belum lengkap") -> LIC > LRC | F11: Komposisi kewajiban

Sheet IFRS9_Analysis
A1: ANALISIS KHUSUS IFRS 9 / PSAK 109 – ASURANSI UMUM
A2: Indikator | B2: CY | C2: PY | D2: Perubahan | E2: Interpretasi otomatis | F2: Fokus analisis | G2: Catatan
A3: Financial assets subject to ECL | B3: =Input_IFRS9_Detail!C8 -> 0 | C3: =Input_IFRS9_Detail!D8 -> 0 | D3: =IFERROR((B3/C3)-1,"") | E3: =IF(B3>0,"Basis ECL tersedia","Belum diisi") -> Belum diisi | F3: Ruang lingkup ECL
A4: Total allowance ECL | B4: =Input_IFRS9_Detail!C15 -> 0 | C4: =Input_IFRS9_Detail!D15 -> 0 | D4: =IFERROR((B4/C4)-1,"") | E4: =IF(B4>0,"Allowance ECL tersedia","Belum diisi") -> Belum diisi | F4: Cadangan kerugian
A5: ECL coverage | B5: =Rasio!D15 | C5: =Rasio!E15 | D5: =IFERROR((B5/C5)-1,"") | E5: =IF(B5>=Setup!$B$20,"Coverage memadai","Coverage tipis / incomplete") -> Coverage memadai | F5: Kehati-hatian kredit
A6: Stage 2+3 ratio | B6: =Rasio!D16 | C6: =Rasio!E16 | D6: =IFERROR((B6/C6)-1,"") | E6: =IF(B6<=Setup!$B$21,"Migrasi kredit terkendali","Migrasi kredit meningkat") -> Migrasi kredit meningkat | F6: Kualitas portofolio
A7: FVOCI reserve | B7: =Input_IFRS9_Detail!C21 -> 0 | C7: =Input_IFRS9_Detail!D21 -> 0 | D7: =IFERROR((B7/C7)-1,"") | E7: =IF(B7>=0,"Cadangan OCI positif","Cadangan OCI negatif") -> Cadangan OCI positif | F7: Sensitivitas pasar
A8: Portfolio yield | B8: =Input_IFRS9_Detail!C25 | C8: =Input_IFRS9_Detail!D25 | D8: =IFERROR((B8/C8)-1,"") | E8: =IF(B8>0,"Yield investasi tersedia","Belum diisi") -> Yield investasi tersedia | F8: Kinerja investasi
A9: Credit-impaired exposure | B9: =Input_IFRS9_Detail!C18 -> 0 | C9: =Input_IFRS9_Detail!D18 -> 0 | D9: =IFERROR((B9/C9)-1,"") | E9: =IF(B9>0,"Ada exposure bermasalah","Tidak ada / belum diisi") -> Tidak ada / belum diisi | F9: Stage 3

Sheet Auto_Analysis
A1: RINGKASAN OTOMATIS / EXECUTIVE SUMMARY – ASURANSI UMUM
A3: Perusahaan | B3: =Setup!B3 -> <isi nama perusahaan>
A4: Periode | B4: =Setup!B5 -> 2025
A5: Executive summary | B5: ="Perusahaan " & Setup!B3 & " dianalisis sebagai entitas asuransi umum untuk tahun " & Setup!B5 & ". "& IF(Rasio!D3<>"","ROA " & TEXT(Rasio!D3,"0.0%") & ", ","")& IF(Rasio!D4<>"","ROE " & TEXT(Rasio!D4,"0.0%") & ", ","")& IF(Rasio!D7<>"","Combined ratio " & TEXT(Rasio!D7,"0.0%") & ". ","")& IF(Rasio!D8>=Setup!B20,"Retensi memadai. ","Ketergantungan reasuransi relatif tinggi. ")& IF(Rasio!D13>=Setup!B21,"Coverage ECL memadai. ","Coverage ECL tipis / belum lengkap. ") -> Perusahaan <isi nama perusahaan> dianalisis sebagai entitas asuransi umum untuk tahun 2025. Retensi memadai. Coverage ECL memadai.
A7: 1. Skala & struktur neraca | B7: ="Total aset " & TEXT(Input_SFP!C18,"#,##0") & ", total liabilitas " & TEXT(Input_SFP!C26,"#,##0") & ", total ekuitas " & TEXT(Input_SFP!C34,"#,##0") & ". "& IF(Rasio!D11<=Setup!B14,"Leverage neraca masih terkendali.","Leverage neraca tinggi.") -> Total aset ,0, total liabilitas ,0, total ekuitas ,0. Leverage neraca tinggi.
A8: 2. Profitabilitas | B8: ="Profit tahun berjalan " & TEXT(Input_PL_OCI!C16,"#,##0") & " dengan ROE " & TEXT(Rasio!D4,"0.0%") & " dan combined ratio " & TEXT(Rasio!D7,"0.0%") & ". "& IF(Rasio!D7<=Setup!B19,"Kinerja underwriting relatif sehat.","Profit underwriting tertekan.") -> Profit tahun berjalan ,0 dengan ROE dan combined ratio . Profit underwriting tertekan.
A9: 3. Kualitas hasil jasa asuransi (IFRS 17) | B9: ="Insurance revenue " & TEXT(Input_IFRS17_Detail!C3,"#,##0") & ", gross claims incurred " & TEXT(Input_IFRS17_Detail!C4,"#,##0") & ", retention ratio " & TEXT(Rasio!D8,"0.0%") & ", reserve leverage " & TEXT(Rasio!D9,"0.00x") & ". "& IF(Rasio!D9<=Setup!B24,"Cadangan teknis relatif tertopang modal.","Cadangan teknis berat dibanding modal.") -> Insurance revenue ,0, gross claims incurred ,0, retention ratio , reserve leverage . Cadangan teknis berat dibanding modal.
A10: 4. Kualitas aset keuangan (IFRS 9) | B10: ="Aset keuangan subject to ECL " & TEXT(Input_IFRS9_Detail!C8,"#,##0") & ", allowance ECL " & TEXT(Input_IFRS9_Detail!C15,"#,##0") & ", coverage " & TEXT(Rasio!D13,"0.0%") & ", Stage 2+3 ratio " & TEXT(Rasio!D14,"0.0%") & ". "& IF(Rasio!D14<=Setup!B22,"Kualitas portofolio kredit relatif baik.","Ada indikasi peningkatan risiko kredit.") -> Aset keuangan subject to ECL ,0, allowance ECL ,0, coverage , Stage 2+3 ratio . Ada indikasi peningkatan risiko kredit.
A11: 5. Arus kas | B11: ="Arus kas operasi " & TEXT(Input_CF!C3,"#,##0") & " dan OCF/Profit " & TEXT(Rasio!D15,"0.0%") & ". "& IF(Rasio!D15>=Setup!B23,"Konversi laba ke kas baik.","Laba belum kuat terkonversi menjadi kas.") -> Arus kas operasi ,0 dan OCF/Profit . Konversi laba ke kas baik.
A12: 6. Red flags utama | B12: =_xludf.TEXTJOIN("; ",TRUE,IF(Rasio!D7>Setup!B19,"combined ratio di atas ambang",""),IF(Rasio!D8<Setup!B20,"retention ratio rendah",""),IF(Rasio!D9>Setup!B24,"reserve leverage tinggi",""),IF(Rasio!D13<Setup!B21,"coverage ECL tipis / belum lengkap",""),IF(Rasio!D14>Setup!B22,"Stage 2+3 ratio tinggi",""),IF(Rasio!D15<Setup!B23,"arus kas operasi lemah terhadap laba","")) -> #NAME?
A14: Checklist cepat user
A15: IFRS17 utama sudah cukup lengkap? | B15: =IF(COUNTA(Input_IFRS17_Detail!C3:C32)>=10,"Ya","Belum") -> Belum
A16: IFRS9 utama sudah cukup lengkap? | B16: =IF(COUNTA(Input_IFRS9_Detail!C3:C21)>=8,"Ya","Belum") -> Belum
A17: Neraca balance? | B17: =IF(ABS(Input_SFP!C18-Input_SFP!C35)<1,"Ya","Tidak") -> Ya
A18: Kas konsisten? | B18: =IF(ABS(Rasio!D16-1)<0.02,"Ya","Tidak") -> #VALUE!

Sheet Dashboard
A1: DASHBOARD RINGKAS – ASURANSI UMUM IFRS 9 / IFRS 17
A3: Total Aset | B3: =Input_SFP!C18 -> 0 | C3: Total Liabilitas | D3: =Input_SFP!C26 -> 0 | E3: Total Ekuitas | F3: =Input_SFP!C34 -> 0 | G3: Profit Tahun Berjalan | H3: =Input_PL_OCI!C16 -> 0 | I3: Comprehensive Income | J3: =Input_PL_OCI!C21 -> 0
A6: ROA | B6: =Rasio!D3 | C6: ROE | D6: =Rasio!D4 | E6: Combined Ratio | F6: =Rasio!D7 | G6: Retention Ratio | H6: =Rasio!D8 | I6: ECL Coverage | J6: =Rasio!D13
A9: Quick summary | F9: Red flags
A10: =Auto_Analysis!B5 -> Perusahaan <isi nama perusahaan> dianalisis sebagai entitas asuransi umum untuk tahun 2025. Retensi memadai. Coverage ECL memadai. | F10: =Auto_Analysis!B12 -> #NAME?
A13: Checklist
A14: IFRS17 lengkap | B14: =Auto_Analysis!B15 -> Belum
A15: IFRS9 lengkap | B15: =Auto_Analysis!B16 -> Belum
A16: Neraca balance | B16: =Auto_Analysis!B17 -> Ya
A17: Kas konsisten | B17: =Auto_Analysis!B18 -> #VALUE!

Sheet Validasi
A1: VALIDASI INPUT, KONSISTENSI, DAN KONTROL
A2: Kontrol | B2: Hasil | C2: Status | D2: Sheet | E2: Tindak lanjut | F2: Catatan
A3: Total assets = liabilities + dana peserta + equity | B3: =IF(ABS(Input_SFP!C18-Input_SFP!C35)<1,"OK","CEK") -> OK | C3: =B3 -> OK | D3: Input_SFP | E3: Pastikan neraca balance
A4: Cash ending CF = cash SFP | B4: =IF(ABS(Input_CF!C8-Input_SFP!C3)<1,"OK","CEK") -> OK | C4: =B4 -> OK | D4: Input_CF / Input_SFP | E4: Rekonsiliasi arus kas dan neraca
A5: Profit + OCI = Total comprehensive income | B5: =IF(ABS(Input_PL_OCI!C21-(Input_PL_OCI!C16+Input_PL_OCI!C20))<1,"OK","CEK") -> OK | C5: =B5 -> OK | D5: Input_PL_OCI | E5: Periksa laba dan OCI
A6: Insurance service result formula | B6: =IF(ABS(Input_IFRS17_Detail!C9-SUM(Input_IFRS17_Detail!C3:C8))<1,"OK","CEK") -> OK | C6: =B6 -> OK | D6: Input_IFRS17_Detail | E6: Periksa komponen hasil jasa
A7: Insurance result after finance | B7: =IF(ABS(Input_IFRS17_Detail!C12-(Input_IFRS17_Detail!C9+SUM(Input_IFRS17_Detail!C10:C11)))<1,"OK","CEK") -> OK | C7: =B7 -> OK | D7: Input_IFRS17_Detail | E7: Periksa hasil setelah finance
A8: Retention ratio helper | B8: =IF(OR(Input_IFRS17_Detail!C24="",Input_IFRS17_Detail!C25="",ABS(Input_IFRS17_Detail!C26-(Input_IFRS17_Detail!C25/Input_IFRS17_Detail!C24))<0.0001),"OK","CEK") -> #VALUE! | C8: =B8 -> #VALUE! | D8: Input_IFRS17_Detail | E8: Isi GWP/NWP bila memakai retention ratio
A9: Combined ratio helper | B9: =IF(OR(Input_IFRS17_Detail!C28="",Input_IFRS17_Detail!C29="",ABS(Input_IFRS17_Detail!C30-(Input_IFRS17_Detail!C28+Input_IFRS17_Detail!C29))<0.0001),"OK","CEK") -> #VALUE! | C9: =B9 -> #VALUE! | D9: Input_IFRS17_Detail | E9: Periksa loss dan expense ratio
A10: Total financial assets subject to ECL | B10: =IF(ABS(Input_IFRS9_Detail!C8-SUM(Input_IFRS9_Detail!C4,Input_IFRS9_Detail!C6,Input_IFRS9_Detail!C7))<1,"OK","CEK") -> OK | C10: =B10 -> OK | D10: Input_IFRS9_Detail | E10: Periksa basis ECL
A11: Total allowance ECL | B11: =IF(ABS(Input_IFRS9_Detail!C15-SUM(Input_IFRS9_Detail!C12:'Input_IFRS9_Detail'!C14))<1,"OK","CEK") -> OK | C11: =B11 -> OK | D11: Input_IFRS9_Detail | E11: Periksa stage allowance
A12: Minimal input SFP utama terisi | B12: =IF(COUNTA(Input_SFP!C3:C34)>=10,"OK","CEK") -> CEK | C12: =B12 -> CEK | D12: Input_SFP | E12: Isi akun utama minimal
A13: Minimal input P/L utama terisi | B13: =IF(COUNTA(Input_PL_OCI!C3:C19)>=6,"OK","CEK") -> CEK | C13: =B13 -> CEK | D13: Input_PL_OCI | E13: Isi akun P/L utama minimal
A14: Minimal input IFRS17 utama terisi | B14: =IF(COUNTA(Input_IFRS17_Detail!C3:C23)>=10,"OK","CEK") -> CEK | C14: =B14 -> CEK | D14: Input_IFRS17_Detail | E14: Isi revenue, klaim, cadangan, RA
A15: Minimal input IFRS9 utama terisi | B15: =IF(COUNTA(Input_IFRS9_Detail!C3:C21)>=8,"OK","CEK") -> CEK | C15: =B15 -> CEK | D15: Input_IFRS9_Detail | E15: Isi klasifikasi aset & ECL
