Workbook

Sheet README
A1: TEMPLATE ANALISIS LAPORAN KEUANGAN ASURANSI JIWA – IFRS 9 / IFRS 17 (VERSI 4 EXTREME REBUILD)
A3: Cara pakai
A4: 1. Isi angka audited report di sheet RAW_* (sel input berwarna kuning, font biru).
A5: 2. Kolom 'Mapping code' menentukan ke akun standar IFRS 9/IFRS 17 yang dianalisis otomatis.
A6: 3. Sheet INPUT_* mengambil angka dari sheet RAW_* dengan formula SUMIFS, jadi Anda bisa menambah baris input bila perlu.
A7: 4. Sheet Rasio, CommonSize_Trend, IFRS17_Analysis, IFRS9_Analysis, Scorecard, Auto_Analysis, dan Dashboard akan terisi otomatis.
A8: 5. Untuk laporan yang punya 3 tahun komparatif, isi kolom CY, PY, dan PPY. Jika tidak ada, kolom PPY boleh kosong.
A9: 6. Gunakan kode DETAIL_ONLY bila ingin menyimpan angka audited report di raw sheet tanpa memengaruhi mapping summary.
A10: 7. Validasi utama: neraca balance, ending cash konsisten, profit + OCI = comprehensive income, helper IFRS 17/9 konsisten.
A11: 8. Template ini dirancang generik untuk perusahaan yang sudah menerapkan IFRS 9 / IFRS 17; beberapa akun lokal tetap perlu judgement mapping.
A12: 9. Versi 4 menambahkan narasi equity-research style, red flags regulator, underwriting quality, reserve quality, reinsurance dependence, dan earnings quality.
A13: 10. Sheet baru V4: Equity_Research, Regulatory_Flags, Underwriting_Quality, Reserve_Quality, Reinsurance_Dependence, Earnings_Quality.
A14: 11. Untuk perusahaan terisi, sheet-sheet V4 akan menghasilkan narasi otomatis berbasis formula dan rasio pada workbook ini.
A15: Input user | B15: Sel kuning, font biru
A16: Formula | B16: Font hitam
A17: Static / note | B17: Abu-abu
A18: Sheet raw | B18: Sumber angka audited report
A19: Sheet input | B19: Ringkasan mapped ke akun standar
A21: V5 supervisory revision notes
A22: Sign convention V5: insurance revenue is positive; claims/benefits, acquisition costs, attributable expenses, and onerous losses are input as positive expenses and deducted by formulas.
A23: Reinsurance net result V5: input positive if net income/recovery from reinsurance held; input negative if net expense from reinsurance held.
A24: CSM V5: CSM recognised for services provided is input positive as release and deducted from closing CSM.
A25: Validation V5: blank/all-zero input is flagged as NO DATA, not OK.
A26: IFRS 9 V5: ECL base is reconciled to Stage 1 + Stage 2 + Stage 3 gross exposure.
A27: Scorecard V5: metrics with no data/blank denominator do not receive points.

Sheet Setup
A1: SETUP, PARAMETER, DAN BENCHMARK
A3: Parameter | B3: Nilai | C3: Keterangan
A4: Nama perusahaan
A5: Sektor | B5: Asuransi Jiwa
A6: Periode analisis | B6: FY 20XX
A7: Mata uang | B7: IDR
A8: Unit | B8: million Rupiah
A9: Sumber | B9: Audited financial statements
A12: Threshold
A13: Liquidity / cash to liabilities minimum | B13: 0.05
A14: Leverage / liabilities to equity maximum | B14: 3
A15: ROA minimum | B15: 0.01
A16: ROE minimum | B16: 0.05
A17: Claim / loss ratio maximum | B17: 0.7
A18: Expense ratio maximum | B18: 0.35
A19: Combined ratio maximum | B19: 1
A20: Retention ratio minimum | B20: 0.35
A21: ECL coverage minimum | B21: 0.002
A22: Stage 2+3 ratio maximum | B22: 0.1
A23: OCF / profit minimum | B23: 0.8
A24: Reserve leverage maximum | B24: 3
... A27: Retro / reinsurance dependence maximum | B27: 0.7

Sheet Raw_SFP
A1: RAW INPUT – STATEMENT OF FINANCIAL POSITION
A2: Kelompok | B2: Raw audited line item | C2: CY | D2: PY | E2: PPY | F2: Mapping code | G2: Include in summary (Y/N) | H2: Source / page | I2: Notes
A3: Statement | B3: Cash and bank | F3: SFP_CASH | G3: Y | H3: Audited SFP
A4: Statement | B4: Time deposits / money market placement | F4: SFP_MM | G4: Y | H4: Audited SFP/notes
A5: Classification | B5: Investments at FVTPL | F5: SFP_FVTPL | G5: Y | H5: IFRS 9 note
A6: Classification | B6: Debt investments at FVOCI | F6: SFP_FVOCI_DEBT | G6: Y | H6: IFRS 9 note
A7: Classification | B7: Equity investments at FVOCI | F7: SFP_FVOCI_EQ | G7: Y | H7: IFRS 9 note
A8: Classification | B8: Investments at amortised cost | F8: SFP_AC | G8: Y | H8: IFRS 9 note
A9: Statement | B9: Policy loans / mortgage loans | F9: SFP_LOANS | G9: Y | H9: Audited SFP/notes
A10: Statement | B10: Premium and other receivables | F10: SFP_RECEIV | G10: Y | H10: Audited SFP
A11: Statement | B11: Reinsurance contract assets | F11: SFP_REINS_ASSET | G11: Y | H11: IFRS 17 note
A12: Statement | B12: Acquisition cash flow asset | F12: SFP_ACQASSET | G12: Y | H12: IFRS 17 note
A13: Statement | B13: Fixed assets and ROU assets | F13: SFP_PPE | G13: Y | H13: Audited SFP
A14: Statement | B14: Tax asset | F14: SFP_TAX_ASSET | G14: Y | H14: Tax note
... A29: Equity | B29: Other reserves | F29: SFP_OTHER_EQ | G29: Y | H29: Equity note

Sheet Raw_PL_OCI
A1: RAW INPUT – PROFIT OR LOSS & OCI
A2: Kelompok | B2: Raw audited line item | C2: CY | D2: PY | E2: PPY | F2: Mapping code | G2: Include in summary (Y/N) | H2: Source / page | I2: Notes
A3: Statement | B3: Insurance revenue | F3: PL_INS_REV | G3: Y | H3: Audited P/L
A4: Statement | B4: Insurance service expense | F4: PL_INS_EXP | G4: Y | H4: Audited P/L
A5: Statement | B5: Net reinsurance result | F5: PL_REINS_NET | G5: Y | H5: Audited P/L
A6: Statement | B6: Investment result | F6: PL_INV_RES | G6: Y | H6: Audited P/L
A7: Statement | B7: Insurance finance result - issued | F7: PL_IF_FIN | G7: Y | H7: Audited P/L
A8: Statement | B8: Insurance finance result - reinsurance | F8: PL_REINS_FIN | G8: Y | H8: Audited P/L
A9: Statement | B9: Impairment / ECL on financial assets | F9: PL_IMPAIR | G9: Y | H9: Audited P/L
A10: Statement | B10: Fees / brokerage / other income | F10: PL_FEE_OTHER | G10: Y | H10: Audited P/L
A11: Statement | B11: Operating expenses outside service expense | F11: PL_OPEX | G11: Y | H11: Audited P/L
A12: Statement | B12: Other non-operating items | F12: PL_OTHER_NONOP | G12: Y | H12: Audited P/L
A13: Statement | B13: Income tax expense | F13: PL_TAX | G13: Y | H13: Audited P/L
A14: OCI | B14: FVOCI reserve movement | F14: OCI_FVOCI | G14: Y | H14: OCI
... A16: OCI | B16: Other OCI | F16: OCI_OTHER | G16: Y | H16: OCI

Sheet Raw_CF
A1: RAW INPUT – CASH FLOWS
A2: Kelompok | B2: Raw audited line item | C2: CY | D2: PY | E2: PPY | F2: Mapping code | G2: Include in summary (Y/N) | H2: Source / page | I2: Notes
A3: Operating | B3: Operating cash flow | F3: CF_OPER | G3: Y | H3: Audited CF
A4: Investing | B4: Investing cash flow | F4: CF_INVEST | G4: Y | H4: Audited CF
A5: Financing | B5: Financing cash flow | F5: CF_FIN | G5: Y | H5: Audited CF
A6: Reconciling | B6: FX / other reconciling item | F6: CF_OTHER | G6: Y | H6: Audited CF | I6: optional; 0 if not disclosed
A7: Balance | B7: Opening cash | F7: CF_BEGIN | G7: Y | H7: Audited CF

Sheet Raw_IFRS17
A1: RAW INPUT – IFRS 17 / PSAK 117 (ASURANSI JIWA)
A2: Kelompok | B2: Raw audited line item | C2: CY | D2: PY | E2: PPY | F2: Mapping code | G2: Include in summary (Y/N) | H2: Source / page | I2: Notes
A3: Hasil jasa | B3: Insurance revenue total | F3: I17_REV | G3: Y | H3: IFRS 17 note
A4: Hasil jasa | B4: Claims and benefits incurred | F4: I17_CLAIMS | G4: Y | H4: IFRS 17 note | I4: V5: input positif sebagai beban/loss; formula akan mengurangkan dari insurance service result.
A5: Hasil jasa | B5: Acquisition cash flow amortisation / commissions in service expense | F5: I17_ACQ_AMORT | G5: Y | H5: IFRS 17 note | I5: V5: input positif sebagai beban/loss; formula akan mengurangkan dari insurance service result.
A6: Hasil jasa | B6: Other directly attributable expenses | F6: I17_OTHER_EXP | G6: Y | H6: IFRS 17 note | I6: V5: input positif sebagai beban/loss; formula akan mengurangkan dari insurance service result.
A7: Hasil jasa | B7: Losses on onerous contracts and reversals | F7: I17_ONEROUS | G7: Y | H7: IFRS 17 note | I7: V5: input positif sebagai beban/loss; formula akan mengurangkan dari insurance service result.
A8: Reasuransi | B8: Net expense/(income) from reinsurance contracts held | F8: I17_REINS_NET | G8: Y | H8: IFRS 17 note | I8: V5: input positif jika net income/recovery; negatif jika net expense dari reinsurance held.
A9: Keuangan | B9: Insurance finance income/(expense) - contracts issued | F9: I17_FIN_ISSUED | G9: Y | H9: IFRS 17 note
A10: Keuangan | B10: Insurance finance income/(expense) - reinsurance held | F10: I17_FIN_REINS | G10: Y | H10: IFRS 17 note
A11: Posisi keuangan | B11: Insurance contract liabilities | F11: I17_LIAB | G11: Y | H11: IFRS 17 note
A12: Posisi keuangan | B12: Reinsurance contract assets | F12: I17_REINS_ASSET | G12: Y | H12: IFRS 17 note
A13: Posisi keuangan | B13: Reinsurance contract liabilities | F13: I17_REINS_LIAB | G13: Y | H13: IFRS 17 note
A14: Posisi keuangan | B14: Liability for remaining coverage (LRC) excl. loss component | F14: I17_LRC | G14: Y | H14: IFRS 17 note
A15: Posisi keuangan | B15: Liability for incurred claims (LIC) | F15: I17_LIC | G15: Y | H15: IFRS 17 note
A16: Posisi keuangan | B16: Loss component | F16: I17_LOSSCOMP | G16: Y | H16: IFRS 17 note
A17: Posisi keuangan | B17: Risk adjustment for non-financial risk | F17: I17_RA | G17: Y | H17: IFRS 17 note
A18: CSM | B18: Opening CSM | F18: I17_CSM_OPEN | G18: Y | H18: IFRS 17 note
A19: CSM | B19: New business / contracts issued | F19: I17_CSM_NEW | G19: Y | H19: IFRS 17 note
A20: CSM | B20: Interest accretion on CSM | F20: I17_CSM_ACC | G20: Y | H20: IFRS 17 note
A21: CSM | B21: Changes related to future service | F21: I17_CSM_FUT | G21: Y | H21: IFRS 17 note
A22: CSM | B22: CSM recognised for services provided | F22: I17_CSM_SERV | G22: Y | H22: IFRS 17 note | I22: V5: input positif sebagai CSM release/services provided; formula closing CSM akan mengurangkan.
A23: CSM | B23: FX and other movements | F23: I17_CSM_OTHER | G23: Y | H23: IFRS 17 note
A24: Operasional | B24: Insurance acquisition cash flow asset | F24: I17_ACQASSET | G24: Y | H24: IFRS 17 note
A25: Operasional | B25: Policies in force / coverage units | F25: I17_COV_UNITS | G25: Y | H25: IFRS 17 note
A26: Operasional | B26: New business APE / new premiums | F26: I17_NEWBUS | G26: Y | H26: IFRS 17 note
A27: Operasional | B27: Claim ratio (if disclosed) | F27: I17_CLAIM_RATIO | G27: Y | H27: IFRS 17 note
A28: Operasional | B28: Reinsurance cession ratio (if disclosed) | F28: I17_CESSION | G28: Y | H28: IFRS 17 note
A29: Operasional | B29: Discount rate / locked-in rate (avg) | F29: I17_DISC_RATE | G29: Y | H29: IFRS 17 note

Sheet Raw_IFRS9
A1: RAW INPUT – IFRS 9 / PSAK 109
A2: Kelompok | B2: Raw audited line item | C2: CY | D2: PY | E2: PPY | F2: Mapping code | G2: Include in summary (Y/N) | H2: Source / page | I2: Notes
A3: Aset keuangan | B3: FVTPL carrying amount | F3: I9_FVTPL | G3: Y | H3: IFRS 9 note
A4: Aset keuangan | B4: FVOCI debt instruments carrying amount | F4: I9_FVOCI_DEBT | G4: Y | H4: IFRS 9 note
A5: Aset keuangan | B5: FVOCI equity instruments carrying amount | F5: I9_FVOCI_EQ | G5: Y | H5: IFRS 9 note
A6: Aset keuangan | B6: Amortised cost debt instruments carrying amount | F6: I9_AC_DEBT | G6: Y | H6: IFRS 9 note
A7: Aset keuangan | B7: Loans and receivables carrying amount | F7: I9_LOANS | G7: Y | H7: IFRS 9 note
A8: ECL | B8: Stage 1 gross exposure | F8: I9_STAGE1_EXP | G8: Y | H8: IFRS 9 note
A9: ECL | B9: Stage 2 gross exposure | F9: I9_STAGE2_EXP | G9: Y | H9: IFRS 9 note
A10: ECL | B10: Stage 3 gross exposure | F10: I9_STAGE3_EXP | G10: Y | H10: IFRS 9 note
A11: ECL | B11: Stage 1 allowance | F11: I9_STAGE1_ALL | G11: Y | H11: IFRS 9 note
A12: ECL | B12: Stage 2 allowance | F12: I9_STAGE2_ALL | G12: Y | H12: IFRS 9 note
A13: ECL | B13: Stage 3 allowance | F13: I9_STAGE3_ALL | G13: Y | H13: IFRS 9 note
A14: Kualitas aset | B14: Low credit risk exposure | F14: I9_LOWRISK | G14: Y | H14: IFRS 9 note
... A22: Sensitivitas | B22: Interest rate duration / sensitivity (years) | F22: I9_DURATION | G22: Y | H22: IFRS 9 note

Sheet Input_SFP
A1: INPUT STATEMENT OF FINANCIAL POSITION / LAPORAN POSISI KEUANGAN
A2: Kelompok | B2: Akun standar | C2: CY | D2: PY | E2: PPY | F2: Growth vs PY | G2: Ratio / note | H2: Status | I2: Mapping code
A3: ASET | B3: Kas dan setara kas | C3: =IFERROR(SUMIFS(Raw_SFP!$C:$C,Raw_SFP!$F:$F,$I3,Raw_SFP!$G:$G,"Y"),0) | D3: =IFERROR(SUMIFS(Raw_SFP!$D:$D,Raw_SFP!$F:$F,$I3,Raw_SFP!$G:$G,"Y"),0) | E3: =IFERROR(SUMIFS(Raw_SFP!$E:$E,Raw_SFP!$F:$F,$I3,Raw_SFP!$G:$G,"Y"),0) | F3: =IFERROR((C3/D3)-1,"") | H3: =IF(OR(C3=0,C3=""),"Review / optional","OK") | I3: SFP_CASH
A4: ASET | B4: Penempatan jangka pendek / pasar uang | C4: =IFERROR(SUMIFS(Raw_SFP!$C:$C,Raw_SFP!$F:$F,$I4,Raw_SFP!$G:$G,"Y"),0) | D4: =IFERROR(SUMIFS(Raw_SFP!$D:$D,Raw_SFP!$F:$F,$I4,Raw_SFP!$G:$G,"Y"),0) | E4: =IFERROR(SUMIFS(Raw_SFP!$E:$E,Raw_SFP!$F:$F,$I4,Raw_SFP!$G:$G,"Y"),0) | F4: =IFERROR((C4/D4)-1,"") | H4: =IF(OR(C4=0,C4=""),"Review / optional","OK") | I4: SFP_MM
A5: ASET | B5: Investasi pada FVTPL | C5: =IFERROR(SUMIFS(Raw_SFP!$C:$C,Raw_SFP!$F:$F,$I5,Raw_SFP!$G:$G,"Y"),0) | D5: =IFERROR(SUMIFS(Raw_SFP!$D:$D,Raw_SFP!$F:$F,$I5,Raw_SFP!$G:$G,"Y"),0) | E5: =IFERROR(SUMIFS(Raw_SFP!$E:$E,Raw_SFP!$F:$F,$I5,Raw_SFP!$G:$G,"Y"),0) | F5: =IFERROR((C5/D5)-1,"") | H5: =IF(OR(C5=0,C5=""),"Review / optional","OK") | I5: SFP_FVTPL
A6: ASET | B6: Investasi utang pada FVOCI | C6: =IFERROR(SUMIFS(Raw_SFP!$C:$C,Raw_SFP!$F:$F,$I6,Raw_SFP!$G:$G,"Y"),0) | D6: =IFERROR(SUMIFS(Raw_SFP!$D:$D,Raw_SFP!$F:$F,$I6,Raw_SFP!$G:$G,"Y"),0) | E6: =IFERROR(SUMIFS(Raw_SFP!$E:$E,Raw_SFP!$F:$F,$I6,Raw_SFP!$G:$G,"Y"),0) | F6: =IFERROR((C6/D6)-1,"") | H6: =IF(OR(C6=0,C6=""),"Review / optional","OK") | I6: SFP_FVOCI_DEBT
A7: ASET | B7: Investasi ekuitas pada FVOCI | C7: =IFERROR(SUMIFS(Raw_SFP!$C:$C,Raw_SFP!$F:$F,$I7,Raw_SFP!$G:$G,"Y"),0) | D7: =IFERROR(SUMIFS(Raw_SFP!$D:$D,Raw_SFP!$F:$F,$I7,Raw_SFP!$G:$G,"Y"),0) | E7: =IFERROR(SUMIFS(Raw_SFP!$E:$E,Raw_SFP!$F:$F,$I7,Raw_SFP!$G:$G,"Y"),0) | F7: =IFERROR((C7/D7)-1,"") | H7: =IF(OR(C7=0,C7=""),"Review / optional","OK") | I7: SFP_FVOCI_EQ
A8: ASET | B8: Investasi pada biaya perolehan diamortisasi | C8: =IFERROR(SUMIFS(Raw_SFP!$C:$C,Raw_SFP!$F:$F,$I8,Raw_SFP!$G:$G,"Y"),0) | D8: =IFERROR(SUMIFS(Raw_SFP!$D:$D,Raw_SFP!$F:$F,$I8,Raw_SFP!$G:$G,"Y"),0) | E8: =IFERROR(SUMIFS(Raw_SFP!$E:$E,Raw_SFP!$F:$F,$I8,Raw_SFP!$G:$G,"Y"),0) | F8: =IFERROR((C8/D8)-1,"") | H8: =IF(OR(C8=0,C8=""),"Review / optional","OK") | I8: SFP_AC
A9: ASET | B9: Properti investasi | C9: =IFERROR(SUMIFS(Raw_SFP!$C:$C,Raw_SFP!$F:$F,$I9,Raw_SFP!$G:$G,"Y"),0) | D9: =IFERROR(SUMIFS(Raw_SFP!$D:$D,Raw_SFP!$F:$F,$I9,Raw_SFP!$G:$G,"Y"),0) | E9: =IFERROR(SUMIFS(Raw_SFP!$E:$E,Raw_SFP!$F:$F,$I9,Raw_SFP!$G:$G,"Y"),0) | F9: =IFERROR((C9/D9)-1,"") | H9: =IF(OR(C9=0,C9=""),"Review / optional","OK") | I9: SFP_INVPROP
A10: ASET | B10: Pinjaman polis / piutang pembiayaan / loans | C10: =IFERROR(SUMIFS(Raw_SFP!$C:$C,Raw_SFP!$F:$F,$I10,Raw_SFP!$G:$G,"Y"),0) | D10: =IFERROR(SUMIFS(Raw_SFP!$D:$D,Raw_SFP!$F:$F,$I10,Raw_SFP!$G:$G,"Y"),0) | E10: =IFERROR(SUMIFS(Raw_SFP!$E:$E,Raw_SFP!$F:$F,$I10,Raw_SFP!$G:$G,"Y"),0) | F10: =IFERROR((C10/D10)-1,"") | H10: =IF(OR(C10=0,C10=""),"Review / optional","OK") | I10: SFP_LOANS
A11: ASET | B11: Piutang premi dan piutang lain-lain | C11: =IFERROR(SUMIFS(Raw_SFP!$C:$C,Raw_SFP!$F:$F,$I11,Raw_SFP!$G:$G,"Y"),0) | D11: =IFERROR(SUMIFS(Raw_SFP!$D:$D,Raw_SFP!$F:$F,$I11,Raw_SFP!$G:$G,"Y"),0) | E11: =IFERROR(SUMIFS(Raw_SFP!$E:$E,Raw_SFP!$F:$F,$I11,Raw_SFP!$G:$G,"Y"),0) | F11: =IFERROR((C11/D11)-1,"") | H11: =IF(OR(C11=0,C11=""),"Review / optional","OK") | I11: SFP_RECEIV
A12: ASET | B12: Aset kontrak reasuransi | C12: =IFERROR(SUMIFS(Raw_SFP!$C:$C,Raw_SFP!$F:$F,$I12,Raw_SFP!$G:$G,"Y"),0) | D12: =IFERROR(SUMIFS(Raw_SFP!$D:$D,Raw_SFP!$F:$F,$I12,Raw_SFP!$G:$G,"Y"),0) | E12: =IFERROR(SUMIFS(Raw_SFP!$E:$E,Raw_SFP!$F:$F,$I12,Raw_SFP!$G:$G,"Y"),0) | F12: =IFERROR((C12/D12)-1,"") | H12: =IF(OR(C12=0,C12=""),"Review / optional","OK") | I12: SFP_REINS_ASSET
A13: ASET | B13: Aset akuisisi asuransi / acquisition cash flow asset | C13: =IFERROR(SUMIFS(Raw_SFP!$C:$C,Raw_SFP!$F:$F,$I13,Raw_SFP!$G:$G,"Y"),0) | D13: =IFERROR(SUMIFS(Raw_SFP!$D:$D,Raw_SFP!$F:$F,$I13,Raw_SFP!$G:$G,"Y"),0) | E13: =IFERROR(SUMIFS(Raw_SFP!$E:$E,Raw_SFP!$F:$F,$I13,Raw_SFP!$G:$G,"Y"),0) | F13: =IFERROR((C13/D13)-1,"") | H13: =IF(OR(C13=0,C13=""),"Review / optional","OK") | I13: SFP_ACQASSET
A14: ASET | B14: Aset tetap, ROU, dan properti yang digunakan sendiri | C14: =IFERROR(SUMIFS(Raw_SFP!$C:$C,Raw_SFP!$F:$F,$I14,Raw_SFP!$G:$G,"Y"),0) | D14: =IFERROR(SUMIFS(Raw_SFP!$D:$D,Raw_SFP!$F:$F,$I14,Raw_SFP!$G:$G,"Y"),0) | E14: =IFERROR(SUMIFS(Raw_SFP!$E:$E,Raw_SFP!$F:$F,$I14,Raw_SFP!$G:$G,"Y"),0) | F14: =IFERROR((C14/D14)-1,"") | H14: =IF(OR(C14=0,C14=""),"Review / optional","OK") | I14: SFP_PPE
... A17: ASET | B17: Aset lain-lain | C17: =IFERROR(SUMIFS(Raw_SFP!$C:$C,Raw_SFP!$F:$F,$I17,Raw_SFP!$G:$G,"Y"),0) | D17: =IFERROR(SUMIFS(Raw_SFP!$D:$D,Raw_SFP!$F:$F,$I17,Raw_SFP!$G:$G,"Y"),0) | E17: =IFERROR(SUMIFS(Raw_SFP!$E:$E,Raw_SFP!$F:$F,$I17,Raw_SFP!$G:$G,"Y"),0) | F17: =IFERROR((C17/D17)-1,"") | H17: =IF(OR(C17=0,C17=""),"Review / optional","OK") | I17: SFP_OTHER
A18: ASET | B18: TOTAL ASET | C18: =SUM(C3:C17) | D18: =SUM(D3:D17) | E18: =SUM(E3:E17) | F18: =IFERROR((C18/D18)-1,"")
A19: LIABILITAS | B19: Liabilitas kontrak asuransi | C19: =IFERROR(SUMIFS(Raw_SFP!$C:$C,Raw_SFP!$F:$F,$I19,Raw_SFP!$G:$G,"Y"),0) | D19: =IFERROR(SUMIFS(Raw_SFP!$D:$D,Raw_SFP!$F:$F,$I19,Raw_SFP!$G:$G,"Y"),0) | E19: =IFERROR(SUMIFS(Raw_SFP!$E:$E,Raw_SFP!$F:$F,$I19,Raw_SFP!$G:$G,"Y"),0) | F19: =IFERROR((C19/D19)-1,"") | H19: =IF(OR(C19=0,C19=""),"Review / optional","OK") | I19: SFP_INS_LIAB
A20: LIABILITAS | B20: Liabilitas kontrak reasuransi | C20: =IFERROR(SUMIFS(Raw_SFP!$C:$C,Raw_SFP!$F:$F,$I20,Raw_SFP!$G:$G,"Y"),0) | D20: =IFERROR(SUMIFS(Raw_SFP!$D:$D,Raw_SFP!$F:$F,$I20,Raw_SFP!$G:$G,"Y"),0) | E20: =IFERROR(SUMIFS(Raw_SFP!$E:$E,Raw_SFP!$F:$F,$I20,Raw_SFP!$G:$G,"Y"),0) | F20: =IFERROR((C20/D20)-1,"") | H20: =IF(OR(C20=0,C20=""),"Review / optional","OK") | I20: SFP_REINS_LIAB
A21: LIABILITAS | B21: Liabilitas kontrak investasi | C21: =IFERROR(SUMIFS(Raw_SFP!$C:$C,Raw_SFP!$F:$F,$I21,Raw_SFP!$G:$G,"Y"),0) | D21: =IFERROR(SUMIFS(Raw_SFP!$D:$D,Raw_SFP!$F:$F,$I21,Raw_SFP!$G:$G,"Y"),0) | E21: =IFERROR(SUMIFS(Raw_SFP!$E:$E,Raw_SFP!$F:$F,$I21,Raw_SFP!$G:$G,"Y"),0) | F21: =IFERROR((C21/D21)-1,"") | H21: =IF(OR(C21=0,C21=""),"Review / optional","OK") | I21: SFP_INVEST_LIAB
A22: LIABILITAS | B22: Utang klaim, utang reasuransi, dan utang komisi | C22: =IFERROR(SUMIFS(Raw_SFP!$C:$C,Raw_SFP!$F:$F,$I22,Raw_SFP!$G:$G,"Y"),0) | D22: =IFERROR(SUMIFS(Raw_SFP!$D:$D,Raw_SFP!$F:$F,$I22,Raw_SFP!$G:$G,"Y"),0) | E22: =IFERROR(SUMIFS(Raw_SFP!$E:$E,Raw_SFP!$F:$F,$I22,Raw_SFP!$G:$G,"Y"),0) | F22: =IFERROR((C22/D22)-1,"") | H22: =IF(OR(C22=0,C22=""),"Review / optional","OK") | I22: SFP_PAYABLES
A23: LIABILITAS | B23: Utang pajak kini/deferred tax liability | C23: =IFERROR(SUMIFS(Raw_SFP!$C:$C,Raw_SFP!$F:$F,$I23,Raw_SFP!$G:$G,"Y"),0) | D23: =IFERROR(SUMIFS(Raw_SFP!$D:$D,Raw_SFP!$F:$F,$I23,Raw_SFP!$G:$G,"Y"),0) | E23: =IFERROR(SUMIFS(Raw_SFP!$E:$E,Raw_SFP!$F:$F,$I23,Raw_SFP!$G:$G,"Y"),0) | F23: =IFERROR((C23/D23)-1,"") | H23: =IF(OR(C23=0,C23=""),"Review / optional","OK") | I23: SFP_TAX_LIAB
A24: LIABILITAS | B24: Liabilitas sewa dan pinjaman | C24: =IFERROR(SUMIFS(Raw_SFP!$C:$C,Raw_SFP!$F:$F,$I24,Raw_SFP!$G:$G,"Y"),0) | D24: =IFERROR(SUMIFS(Raw_SFP!$D:$D,Raw_SFP!$F:$F,$I24,Raw_SFP!$G:$G,"Y"),0) | E24: =IFERROR(SUMIFS(Raw_SFP!$E:$E,Raw_SFP!$F:$F,$I24,Raw_SFP!$G:$G,"Y"),0) | F24: =IFERROR((C24/D24)-1,"") | H24: =IF(OR(C24=0,C24=""),"Review / optional","OK") | I24: SFP_LEASE_DEBT
A25: LIABILITAS | B25: Liabilitas lain-lain | C25: =IFERROR(SUMIFS(Raw_SFP!$C:$C,Raw_SFP!$F:$F,$I25,Raw_SFP!$G:$G,"Y"),0) | D25: =IFERROR(SUMIFS(Raw_SFP!$D:$D,Raw_SFP!$F:$F,$I25,Raw_SFP!$G:$G,"Y"),0) | E25: =IFERROR(SUMIFS(Raw_SFP!$E:$E,Raw_SFP!$F:$F,$I25,Raw_SFP!$G:$G,"Y"),0) | F25: =IFERROR((C25/D25)-1,"") | H25: =IF(OR(C25=0,C25=""),"Review / optional","OK") | I25: SFP_OTHER_LIAB
A26: LIABILITAS | B26: TOTAL LIABILITAS | C26: =SUM(C19:C25) | D26: =SUM(D19:D25) | E26: =SUM(E19:E25) | F26: =IFERROR((C26/D26)-1,"")
A27: DANA PESERTA | B27: Dana peserta / liabilities to policyholders fund | C27: =IFERROR(SUMIFS(Raw_SFP!$C:$C,Raw_SFP!$F:$F,$I27,Raw_SFP!$G:$G,"Y"),0) | D27: =IFERROR(SUMIFS(Raw_SFP!$D:$D,Raw_SFP!$F:$F,$I27,Raw_SFP!$G:$G,"Y"),0) | E27: =IFERROR(SUMIFS(Raw_SFP!$E:$E,Raw_SFP!$F:$F,$I27,Raw_SFP!$G:$G,"Y"),0) | F27: =IFERROR((C27/D27)-1,"") | H27: =IF(OR(C27=0,C27=""),"Review / optional","OK") | I27: SFP_FUNDS
A28: EKUITAS | B28: Modal saham | C28: =IFERROR(SUMIFS(Raw_SFP!$C:$C,Raw_SFP!$F:$F,$I28,Raw_SFP!$G:$G,"Y"),0) | D28: =IFERROR(SUMIFS(Raw_SFP!$D:$D,Raw_SFP!$F:$F,$I28,Raw_SFP!$G:$G,"Y"),0) | E28: =IFERROR(SUMIFS(Raw_SFP!$E:$E,Raw_SFP!$F:$F,$I28,Raw_SFP!$G:$G,"Y"),0) | F28: =IFERROR((C28/D28)-1,"") | H28: =IF(OR(C28=0,C28=""),"Review / optional","OK") | I28: SFP_SHARECAP
A29: EKUITAS | B29: Tambahan modal disetor | C29: =IFERROR(SUMIFS(Raw_SFP!$C:$C,Raw_SFP!$F:$F,$I29,Raw_SFP!$G:$G,"Y"),0) | D29: =IFERROR(SUMIFS(Raw_SFP!$D:$D,Raw_SFP!$F:$F,$I29,Raw_SFP!$G:$G,"Y"),0) | E29: =IFERROR(SUMIFS(Raw_SFP!$E:$E,Raw_SFP!$F:$F,$I29,Raw_SFP!$G:$G,"Y"),0) | F29: =IFERROR((C29/D29)-1,"") | H29: =IF(OR(C29=0,C29=""),"Review / optional","OK") | I29: SFP_APIC
A30: EKUITAS | B30: Saldo laba | C30: =IFERROR(SUMIFS(Raw_SFP!$C:$C,Raw_SFP!$F:$F,$I30,Raw_SFP!$G:$G,"Y"),0) | D30: =IFERROR(SUMIFS(Raw_SFP!$D:$D,Raw_SFP!$F:$F,$I30,Raw_SFP!$G:$G,"Y"),0) | E30: =IFERROR(SUMIFS(Raw_SFP!$E:$E,Raw_SFP!$F:$F,$I30,Raw_SFP!$G:$G,"Y"),0) | F30: =IFERROR((C30/D30)-1,"") | H30: =IF(OR(C30=0,C30=""),"Review / optional","OK") | I30: SFP_RETAINED
A31: EKUITAS | B31: Cadangan FVOCI / fair value reserve | C31: =IFERROR(SUMIFS(Raw_SFP!$C:$C,Raw_SFP!$F:$F,$I31,Raw_SFP!$G:$G,"Y"),0) | D31: =IFERROR(SUMIFS(Raw_SFP!$D:$D,Raw_SFP!$F:$F,$I31,Raw_SFP!$G:$G,"Y"),0) | E31: =IFERROR(SUMIFS(Raw_SFP!$E:$E,Raw_SFP!$F:$F,$I31,Raw_SFP!$G:$G,"Y"),0) | F31: =IFERROR((C31/D31)-1,"") | H31: =IF(OR(C31=0,C31=""),"Review / optional","OK") | I31: SFP_FVOCI_RES
A32: EKUITAS | B32: Cadangan insurance finance OCI | C32: =IFERROR(SUMIFS(Raw_SFP!$C:$C,Raw_SFP!$F:$F,$I32,Raw_SFP!$G:$G,"Y"),0) | D32: =IFERROR(SUMIFS(Raw_SFP!$D:$D,Raw_SFP!$F:$F,$I32,Raw_SFP!$G:$G,"Y"),0) | E32: =IFERROR(SUMIFS(Raw_SFP!$E:$E,Raw_SFP!$F:$F,$I32,Raw_SFP!$G:$G,"Y"),0) | F32: =IFERROR((C32/D32)-1,"") | H32: =IF(OR(C32=0,C32=""),"Review / optional","OK") | I32: SFP_IFOCI_RES
A33: EKUITAS | B33: Cadangan OCI dan cadangan lain-lain | C33: =IFERROR(SUMIFS(Raw_SFP!$C:$C,Raw_SFP!$F:$F,$I33,Raw_SFP!$G:$G,"Y"),0) | D33: =IFERROR(SUMIFS(Raw_SFP!$D:$D,Raw_SFP!$F:$F,$I33,Raw_SFP!$G:$G,"Y"),0) | E33: =IFERROR(SUMIFS(Raw_SFP!$E:$E,Raw_SFP!$F:$F,$I33,Raw_SFP!$G:$G,"Y"),0) | F33: =IFERROR((C33/D33)-1,"") | H33: =IF(OR(C33=0,C33=""),"Review / optional","OK") | I33: SFP_OTHER_EQ
A34: EKUITAS | B34: TOTAL EKUITAS | C34: =SUM(C28:C33) | D34: =SUM(D28:D33) | E34: =SUM(E28:E33) | F34: =IFERROR((C34/D34)-1,"")
A35: KONTROL | B35: TOTAL LIAB + DANA PESERTA + EKUITAS | C35: =C26+C27+C34 | D35: =D26+D27+D34 | E35: =E26+E27+E34 | F35: =IFERROR((C35/D35)-1,"") | G35: Balance check

Sheet Input_PL_OCI
A1: INPUT PROFIT OR LOSS & OTHER COMPREHENSIVE INCOME
A2: Kelompok | B2: Akun standar | C2: CY | D2: PY | E2: PPY | F2: Growth vs PY | G2: Ratio / note | H2: Status | I2: Mapping code
A3: HASIL JASA ASURANSI | B3: Insurance revenue | C3: =IFERROR(SUMIFS(Raw_PL_OCI!$C:$C,Raw_PL_OCI!$F:$F,$I3,Raw_PL_OCI!$G:$G,"Y"),0) | D3: =IFERROR(SUMIFS(Raw_PL_OCI!$D:$D,Raw_PL_OCI!$F:$F,$I3,Raw_PL_OCI!$G:$G,"Y"),0) | E3: =IFERROR(SUMIFS(Raw_PL_OCI!$E:$E,Raw_PL_OCI!$F:$F,$I3,Raw_PL_OCI!$G:$G,"Y"),0) | F3: =IFERROR((C3/D3)-1,"") | H3: =IF(OR(C3=0,C3=""),"Review / optional","OK") | I3: PL_INS_REV
A4: HASIL JASA ASURANSI | B4: Insurance service expense | C4: =IFERROR(SUMIFS(Raw_PL_OCI!$C:$C,Raw_PL_OCI!$F:$F,$I4,Raw_PL_OCI!$G:$G,"Y"),0) | D4: =IFERROR(SUMIFS(Raw_PL_OCI!$D:$D,Raw_PL_OCI!$F:$F,$I4,Raw_PL_OCI!$G:$G,"Y"),0) | E4: =IFERROR(SUMIFS(Raw_PL_OCI!$E:$E,Raw_PL_OCI!$F:$F,$I4,Raw_PL_OCI!$G:$G,"Y"),0) | F4: =IFERROR((C4/D4)-1,"") | H4: =IF(OR(C4=0,C4=""),"Review / optional","OK") | I4: PL_INS_EXP
A5: HASIL JASA ASURANSI | B5: Net expense/(income) from reinsurance contracts held | C5: =IFERROR(SUMIFS(Raw_PL_OCI!$C:$C,Raw_PL_OCI!$F:$F,$I5,Raw_PL_OCI!$G:$G,"Y"),0) | D5: =IFERROR(SUMIFS(Raw_PL_OCI!$D:$D,Raw_PL_OCI!$F:$F,$I5,Raw_PL_OCI!$G:$G,"Y"),0) | E5: =IFERROR(SUMIFS(Raw_PL_OCI!$E:$E,Raw_PL_OCI!$F:$F,$I5,Raw_PL_OCI!$G:$G,"Y"),0) | F5: =IFERROR((C5/D5)-1,"") | H5: =IF(OR(C5=0,C5=""),"Review / optional","OK") | I5: PL_REINS_NET
A6: HASIL JASA ASURANSI | B6: INSURANCE SERVICE RESULT | C6: =SUM(C3:C5) | D6: =SUM(D3:D5) | E6: =SUM(E3:E5) | F6: =IFERROR((C6/D6)-1,"") | G6: V5 cross-check: harus direkonsiliasi dengan IFRS17 service result; perhatikan tanda audited P/L.
A7: INVESTASI & KEUANGAN | B7: Net investment result / investment income - net | C7: =IFERROR(SUMIFS(Raw_PL_OCI!$C:$C,Raw_PL_OCI!$F:$F,$I7,Raw_PL_OCI!$G:$G,"Y"),0) | D7: =IFERROR(SUMIFS(Raw_PL_OCI!$D:$D,Raw_PL_OCI!$F:$F,$I7,Raw_PL_OCI!$G:$G,"Y"),0) | E7: =IFERROR(SUMIFS(Raw_PL_OCI!$E:$E,Raw_PL_OCI!$F:$F,$I7,Raw_PL_OCI!$G:$G,"Y"),0) | F7: =IFERROR((C7/D7)-1,"") | H7: =IF(OR(C7=0,C7=""),"Review / optional","OK") | I7: PL_INV_RES
A8: INVESTASI & KEUANGAN | B8: Insurance finance income/(expense) from contracts issued | C8: =IFERROR(SUMIFS(Raw_PL_OCI!$C:$C,Raw_PL_OCI!$F:$F,$I8,Raw_PL_OCI!$G:$G,"Y"),0) | D8: =IFERROR(SUMIFS(Raw_PL_OCI!$D:$D,Raw_PL_OCI!$F:$F,$I8,Raw_PL_OCI!$G:$G,"Y"),0) | E8: =IFERROR(SUMIFS(Raw_PL_OCI!$E:$E,Raw_PL_OCI!$F:$F,$I8,Raw_PL_OCI!$G:$G,"Y"),0) | F8: =IFERROR((C8/D8)-1,"") | H8: =IF(OR(C8=0,C8=""),"Review / optional","OK") | I8: PL_IF_FIN
A9: INVESTASI & KEUANGAN | B9: Insurance finance income/(expense) from reinsurance held | C9: =IFERROR(SUMIFS(Raw_PL_OCI!$C:$C,Raw_PL_OCI!$F:$F,$I9,Raw_PL_OCI!$G:$G,"Y"),0) | D9: =IFERROR(SUMIFS(Raw_PL_OCI!$D:$D,Raw_PL_OCI!$F:$F,$I9,Raw_PL_OCI!$G:$G,"Y"),0) | E9: =IFERROR(SUMIFS(Raw_PL_OCI!$E:$E,Raw_PL_OCI!$F:$F,$I9,Raw_PL_OCI!$G:$G,"Y"),0) | F9: =IFERROR((C9/D9)-1,"") | H9: =IF(OR(C9=0,C9=""),"Review / optional","OK") | I9: PL_REINS_FIN
A10: INVESTASI & KEUANGAN | B10: Net impairment gain/(loss) on financial assets | C10: =IFERROR(SUMIFS(Raw_PL_OCI!$C:$C,Raw_PL_OCI!$F:$F,$I10,Raw_PL_OCI!$G:$G,"Y"),0) | D10: =IFERROR(SUMIFS(Raw_PL_OCI!$D:$D,Raw_PL_OCI!$F:$F,$I10,Raw_PL_OCI!$G:$G,"Y"),0) | E10: =IFERROR(SUMIFS(Raw_PL_OCI!$E:$E,Raw_PL_OCI!$F:$F,$I10,Raw_PL_OCI!$G:$G,"Y"),0) | F10: =IFERROR((C10/D10)-1,"") | H10: =IF(OR(C10=0,C10=""),"Review / optional","OK") | I10: PL_IMPAIR
A11: INVESTASI & KEUANGAN | B11: Fee and other operating income | C11: =IFERROR(SUMIFS(Raw_PL_OCI!$C:$C,Raw_PL_OCI!$F:$F,$I11,Raw_PL_OCI!$G:$G,"Y"),0) | D11: =IFERROR(SUMIFS(Raw_PL_OCI!$D:$D,Raw_PL_OCI!$F:$F,$I11,Raw_PL_OCI!$G:$G,"Y"),0) | E11: =IFERROR(SUMIFS(Raw_PL_OCI!$E:$E,Raw_PL_OCI!$F:$F,$I11,Raw_PL_OCI!$G:$G,"Y"),0) | F11: =IFERROR((C11/D11)-1,"") | H11: =IF(OR(C11=0,C11=""),"Review / optional","OK") | I11: PL_FEE_OTHER
A12: BEBAN | B12: Operating expenses outside insurance service expense | C12: =IFERROR(SUMIFS(Raw_PL_OCI!$C:$C,Raw_PL_OCI!$F:$F,$I12,Raw_PL_OCI!$G:$G,"Y"),0) | D12: =IFERROR(SUMIFS(Raw_PL_OCI!$D:$D,Raw_PL_OCI!$F:$F,$I12,Raw_PL_OCI!$G:$G,"Y"),0) | E12: =IFERROR(SUMIFS(Raw_PL_OCI!$E:$E,Raw_PL_OCI!$F:$F,$I12,Raw_PL_OCI!$G:$G,"Y"),0) | F12: =IFERROR((C12/D12)-1,"") | H12: =IF(OR(C12=0,C12=""),"Review / optional","OK") | I12: PL_OPEX
A13: BEBAN | B13: Finance costs and other non-operating items | C13: =IFERROR(SUMIFS(Raw_PL_OCI!$C:$C,Raw_PL_OCI!$F:$F,$I13,Raw_PL_OCI!$G:$G,"Y"),0) | D13: =IFERROR(SUMIFS(Raw_PL_OCI!$D:$D,Raw_PL_OCI!$F:$F,$I13,Raw_PL_OCI!$G:$G,"Y"),0) | E13: =IFERROR(SUMIFS(Raw_PL_OCI!$E:$E,Raw_PL_OCI!$F:$F,$I13,Raw_PL_OCI!$G:$G,"Y"),0) | F13: =IFERROR((C13/D13)-1,"") | H13: =IF(OR(C13=0,C13=""),"Review / optional","OK") | I13: PL_OTHER_NONOP
A14: LABA | B14: PROFIT BEFORE TAX | C14: =SUM(C6:C13) | D14: =SUM(D6:D13) | E14: =SUM(E6:E13) | F14: =IFERROR((C14/D14)-1,"")
A15: LABA | B15: Income tax expense | C15: =IFERROR(SUMIFS(Raw_PL_OCI!$C:$C,Raw_PL_OCI!$F:$F,$I15,Raw_PL_OCI!$G:$G,"Y"),0) | D15: =IFERROR(SUMIFS(Raw_PL_OCI!$D:$D,Raw_PL_OCI!$F:$F,$I15,Raw_PL_OCI!$G:$G,"Y"),0) | E15: =IFERROR(SUMIFS(Raw_PL_OCI!$E:$E,Raw_PL_OCI!$F:$F,$I15,Raw_PL_OCI!$G:$G,"Y"),0) | F15: =IFERROR((C15/D15)-1,"") | H15: =IF(OR(C15=0,C15=""),"Review / optional","OK") | I15: PL_TAX
A16: LABA | B16: PROFIT FOR THE YEAR | C16: =SUM(C14:C15) | D16: =SUM(D14:D15) | E16: =SUM(E14:E15) | F16: =IFERROR((C16/D16)-1,"")
A17: OCI | B17: OCI - FVOCI reserve movement | C17: =IFERROR(SUMIFS(Raw_PL_OCI!$C:$C,Raw_PL_OCI!$F:$F,$I17,Raw_PL_OCI!$G:$G,"Y"),0) | D17: =IFERROR(SUMIFS(Raw_PL_OCI!$D:$D,Raw_PL_OCI!$F:$F,$I17,Raw_PL_OCI!$G:$G,"Y"),0) | E17: =IFERROR(SUMIFS(Raw_PL_OCI!$E:$E,Raw_PL_OCI!$F:$F,$I17,Raw_PL_OCI!$G:$G,"Y"),0) | F17: =IFERROR((C17/D17)-1,"") | H17: =IF(OR(C17=0,C17=""),"Review / optional","OK") | I17: OCI_FVOCI
A18: OCI | B18: OCI - insurance finance OCI | C18: =IFERROR(SUMIFS(Raw_PL_OCI!$C:$C,Raw_PL_OCI!$F:$F,$I18,Raw_PL_OCI!$G:$G,"Y"),0) | D18: =IFERROR(SUMIFS(Raw_PL_OCI!$D:$D,Raw_PL_OCI!$F:$F,$I18,Raw_PL_OCI!$G:$G,"Y"),0) | E18: =IFERROR(SUMIFS(Raw_PL_OCI!$E:$E,Raw_PL_OCI!$F:$F,$I18,Raw_PL_OCI!$G:$G,"Y"),0) | F18: =IFERROR((C18/D18)-1,"") | H18: =IF(OR(C18=0,C18=""),"Review / optional","OK") | I18: OCI_IFOCI
A19: OCI | B19: OCI - other OCI | C19: =IFERROR(SUMIFS(Raw_PL_OCI!$C:$C,Raw_PL_OCI!$F:$F,$I19,Raw_PL_OCI!$G:$G,"Y"),0) | D19: =IFERROR(SUMIFS(Raw_PL_OCI!$D:$D,Raw_PL_OCI!$F:$F,$I19,Raw_PL_OCI!$G:$G,"Y"),0) | E19: =IFERROR(SUMIFS(Raw_PL_OCI!$E:$E,Raw_PL_OCI!$F:$F,$I19,Raw_PL_OCI!$G:$G,"Y"),0) | F19: =IFERROR((C19/D19)-1,"") | H19: =IF(OR(C19=0,C19=""),"Review / optional","OK") | I19: OCI_OTHER
A20: OCI | B20: TOTAL OCI | C20: =SUM(C17:C19) | D20: =SUM(D17:D19) | E20: =SUM(E17:E19) | F20: =IFERROR((C20/D20)-1,"")
A21: OCI | B21: TOTAL COMPREHENSIVE INCOME | C21: =C16+C20 | D21: =D16+D20 | E21: =E16+E20 | F21: =IFERROR((C21/D21)-1,"")
A22: KONTROL | B22: TOTAL INCOME (MANAGEMENT VIEW) | C22: =SUM(C3,C7:C11) | D22: =SUM(D3,D7:D11) | E22: =SUM(E3,E7:E11) | F22: =IFERROR((C22/D22)-1,"")

Sheet Input_CF
A1: INPUT STATEMENT OF CASH FLOWS
A2: Kelompok | B2: Akun | C2: CY | D2: PY | E2: PPY | F2: Growth vs PY | G2: Ratio / note | H2: Status | I2: Mapping code
A3: OPERASI | B3: Net cash from/(used in) operating activities | C3: =IFERROR(SUMIFS(Raw_CF!$C:$C,Raw_CF!$F:$F,$I3,Raw_CF!$G:$G,"Y"),0) | D3: =IFERROR(SUMIFS(Raw_CF!$D:$D,Raw_CF!$F:$F,$I3,Raw_CF!$G:$G,"Y"),0) | E3: =IFERROR(SUMIFS(Raw_CF!$E:$E,Raw_CF!$F:$F,$I3,Raw_CF!$G:$G,"Y"),0) | F3: =IFERROR((C3/D3)-1,"") | G3: OCF | I3: CF_OPER
A4: INVESTASI | B4: Net cash from/(used in) investing activities | C4: =IFERROR(SUMIFS(Raw_CF!$C:$C,Raw_CF!$F:$F,$I4,Raw_CF!$G:$G,"Y"),0) | D4: =IFERROR(SUMIFS(Raw_CF!$D:$D,Raw_CF!$F:$F,$I4,Raw_CF!$G:$G,"Y"),0) | E4: =IFERROR(SUMIFS(Raw_CF!$E:$E,Raw_CF!$F:$F,$I4,Raw_CF!$G:$G,"Y"),0) | F4: =IFERROR((C4/D4)-1,"") | I4: CF_INVEST
A5: PENDANAAN | B5: Net cash from/(used in) financing activities | C5: =IFERROR(SUMIFS(Raw_CF!$C:$C,Raw_CF!$F:$F,$I5,Raw_CF!$G:$G,"Y"),0) | D5: =IFERROR(SUMIFS(Raw_CF!$D:$D,Raw_CF!$F:$F,$I5,Raw_CF!$G:$G,"Y"),0) | E5: =IFERROR(SUMIFS(Raw_CF!$E:$E,Raw_CF!$F:$F,$I5,Raw_CF!$G:$G,"Y"),0) | F5: =IFERROR((C5/D5)-1,"") | I5: CF_FIN
A6: REKONSILIASI | B6: Net FX / other reconciling items | C6: =IFERROR(SUMIFS(Raw_CF!$C:$C,Raw_CF!$F:$F,$I6,Raw_CF!$G:$G,"Y"),0) | D6: =IFERROR(SUMIFS(Raw_CF!$D:$D,Raw_CF!$F:$F,$I6,Raw_CF!$G:$G,"Y"),0) | E6: =IFERROR(SUMIFS(Raw_CF!$E:$E,Raw_CF!$F:$F,$I6,Raw_CF!$G:$G,"Y"),0) | F6: =IFERROR((C6/D6)-1,"") | I6: CF_OTHER
A7: NETO | B7: Net increase/(decrease) in cash | C7: =SUM(C3:C6) | D7: =SUM(D3:D6) | E7: =SUM(E3:E6) | F7: =IFERROR((C7/D7)-1,"")
A8: SALDO | B8: Cash and cash equivalents at beginning of year | C8: =IFERROR(SUMIFS(Raw_CF!$C:$C,Raw_CF!$F:$F,$I8,Raw_CF!$G:$G,"Y"),0) | D8: =IFERROR(SUMIFS(Raw_CF!$D:$D,Raw_CF!$F:$F,$I8,Raw_CF!$G:$G,"Y"),0) | E8: =IFERROR(SUMIFS(Raw_CF!$E:$E,Raw_CF!$F:$F,$I8,Raw_CF!$G:$G,"Y"),0) | F8: =IFERROR((C8/D8)-1,"") | I8: CF_BEGIN
A9: SALDO | B9: Cash and cash equivalents at end of year | C9: =C7+C8 | D9: =D7+D8 | E9: =E7+E8 | F9: =IFERROR((C9/D9)-1,"") | G9: Ending cash

Sheet Input_IFRS17_Detail
A1: INPUT DETAIL IFRS 17 / PSAK 117 – ASURANSI JIWA
A2: Kelompok | B2: Akun standar | C2: CY | D2: PY | E2: PPY | F2: Growth vs PY | G2: Ratio / note | H2: Status | I2: Mapping code
A3: Hasil jasa | B3: Insurance revenue total | C3: =IFERROR(SUMIFS(Raw_IFRS17!$C:$C,Raw_IFRS17!$F:$F,$I3,Raw_IFRS17!$G:$G,"Y"),0) | D3: =IFERROR(SUMIFS(Raw_IFRS17!$D:$D,Raw_IFRS17!$F:$F,$I3,Raw_IFRS17!$G:$G,"Y"),0) | E3: =IFERROR(SUMIFS(Raw_IFRS17!$E:$E,Raw_IFRS17!$F:$F,$I3,Raw_IFRS17!$G:$G,"Y"),0) | F3: =IFERROR((C3/D3)-1,"") | H3: =IF(OR(C3=0,C3=""),"Review / optional","OK") | I3: I17_REV
A4: Hasil jasa | B4: Claims and benefits incurred | C4: =IFERROR(SUMIFS(Raw_IFRS17!$C:$C,Raw_IFRS17!$F:$F,$I4,Raw_IFRS17!$G:$G,"Y"),0) | D4: =IFERROR(SUMIFS(Raw_IFRS17!$D:$D,Raw_IFRS17!$F:$F,$I4,Raw_IFRS17!$G:$G,"Y"),0) | E4: =IFERROR(SUMIFS(Raw_IFRS17!$E:$E,Raw_IFRS17!$F:$F,$I4,Raw_IFRS17!$G:$G,"Y"),0) | F4: =IFERROR((C4/D4)-1,"") | H4: =IF(OR(C4=0,C4=""),"Review / optional","OK") | I4: I17_CLAIMS
A5: Hasil jasa | B5: Acquisition cash flow amortisation / commissions in service expense | C5: =IFERROR(SUMIFS(Raw_IFRS17!$C:$C,Raw_IFRS17!$F:$F,$I5,Raw_IFRS17!$G:$G,"Y"),0) | D5: =IFERROR(SUMIFS(Raw_IFRS17!$D:$D,Raw_IFRS17!$F:$F,$I5,Raw_IFRS17!$G:$G,"Y"),0) | E5: =IFERROR(SUMIFS(Raw_IFRS17!$E:$E,Raw_IFRS17!$F:$F,$I5,Raw_IFRS17!$G:$G,"Y"),0) | F5: =IFERROR((C5/D5)-1,"") | H5: =IF(OR(C5=0,C5=""),"Review / optional","OK") | I5: I17_ACQ_AMORT
A6: Hasil jasa | B6: Other directly attributable expenses | C6: =IFERROR(SUMIFS(Raw_IFRS17!$C:$C,Raw_IFRS17!$F:$F,$I6,Raw_IFRS17!$G:$G,"Y"),0) | D6: =IFERROR(SUMIFS(Raw_IFRS17!$D:$D,Raw_IFRS17!$F:$F,$I6,Raw_IFRS17!$G:$G,"Y"),0) | E6: =IFERROR(SUMIFS(Raw_IFRS17!$E:$E,Raw_IFRS17!$F:$F,$I6,Raw_IFRS17!$G:$G,"Y"),0) | F6: =IFERROR((C6/D6)-1,"") | H6: =IF(OR(C6=0,C6=""),"Review / optional","OK") | I6: I17_OTHER_EXP
A7: Hasil jasa | B7: Losses on onerous contracts and reversals | C7: =IFERROR(SUMIFS(Raw_IFRS17!$C:$C,Raw_IFRS17!$F:$F,$I7,Raw_IFRS17!$G:$G,"Y"),0) | D7: =IFERROR(SUMIFS(Raw_IFRS17!$D:$D,Raw_IFRS17!$F:$F,$I7,Raw_IFRS17!$G:$G,"Y"),0) | E7: =IFERROR(SUMIFS(Raw_IFRS17!$E:$E,Raw_IFRS17!$F:$F,$I7,Raw_IFRS17!$G:$G,"Y"),0) | F7: =IFERROR((C7/D7)-1,"") | H7: =IF(OR(C7=0,C7=""),"Review / optional","OK") | I7: I17_ONEROUS
A8: Reasuransi | B8: Net expense/(income) from reinsurance contracts held | C8: =IFERROR(SUMIFS(Raw_IFRS17!$C:$C,Raw_IFRS17!$F:$F,$I8,Raw_IFRS17!$G:$G,"Y"),0) | D8: =IFERROR(SUMIFS(Raw_IFRS17!$D:$D,Raw_IFRS17!$F:$F,$I8,Raw_IFRS17!$G:$G,"Y"),0) | E8: =IFERROR(SUMIFS(Raw_IFRS17!$E:$E,Raw_IFRS17!$F:$F,$I8,Raw_IFRS17!$G:$G,"Y"),0) | F8: =IFERROR((C8/D8)-1,"") | H8: =IF(OR(C8=0,C8=""),"Review / optional","OK") | I8: I17_REINS_NET
A9: Hasil jasa | B9: INSURANCE SERVICE RESULT | C9: =IF(C3=0,"",C3-C4-C5-C6-C7+C8) | D9: =IF(D3=0,"",D3-D4-D5-D6-D7+D8) | E9: =IF(E3=0,"",E3-E4-E5-E6-E7+E8) | F9: =IFERROR((C9/D9)-1,"") | G9: V5: revenue - claims - acquisition - other expense - onerous + reinsurance net result.
A10: Keuangan | B10: Insurance finance income/(expense) - contracts issued | C10: =IFERROR(SUMIFS(Raw_IFRS17!$C:$C,Raw_IFRS17!$F:$F,$I10,Raw_IFRS17!$G:$G,"Y"),0) | D10: =IFERROR(SUMIFS(Raw_IFRS17!$D:$D,Raw_IFRS17!$F:$F,$I10,Raw_IFRS17!$G:$G,"Y"),0) | E10: =IFERROR(SUMIFS(Raw_IFRS17!$E:$E,Raw_IFRS17!$F:$F,$I10,Raw_IFRS17!$G:$G,"Y"),0) | F10: =IFERROR((C10/D10)-1,"") | H10: =IF(OR(C10=0,C10=""),"Review / optional","OK") | I10: I17_FIN_ISSUED
A11: Keuangan | B11: Insurance finance income/(expense) - reinsurance held | C11: =IFERROR(SUMIFS(Raw_IFRS17!$C:$C,Raw_IFRS17!$F:$F,$I11,Raw_IFRS17!$G:$G,"Y"),0) | D11: =IFERROR(SUMIFS(Raw_IFRS17!$D:$D,Raw_IFRS17!$F:$F,$I11,Raw_IFRS17!$G:$G,"Y"),0) | E11: =IFERROR(SUMIFS(Raw_IFRS17!$E:$E,Raw_IFRS17!$F:$F,$I11,Raw_IFRS17!$G:$G,"Y"),0) | F11: =IFERROR((C11/D11)-1,"") | H11: =IF(OR(C11=0,C11=""),"Review / optional","OK") | I11: I17_FIN_REINS
A12: Keuangan | B12: INSURANCE RESULT AFTER FINANCE | C12: =IF(C9="","",C9+C10+C11) | D12: =IF(D9="","",D9+D10+D11) | E12: =IF(E9="","",E9+E10+E11) | F12: =IFERROR((C12/D12)-1,"")
A13: Posisi keuangan | B13: Insurance contract liabilities | C13: =IFERROR(SUMIFS(Raw_IFRS17!$C:$C,Raw_IFRS17!$F:$F,$I13,Raw_IFRS17!$G:$G,"Y"),0) | D13: =IFERROR(SUMIFS(Raw_IFRS17!$D:$D,Raw_IFRS17!$F:$F,$I13,Raw_IFRS17!$G:$G,"Y"),0) | E13: =IFERROR(SUMIFS(Raw_IFRS17!$E:$E,Raw_IFRS17!$F:$F,$I13,Raw_IFRS17!$G:$G,"Y"),0) | F13: =IFERROR((C13/D13)-1,"") | H13: =IF(OR(C13=0,C13=""),"Review / optional","OK") | I13: I17_LIAB
A14: Posisi keuangan | B14: Reinsurance contract assets | C14: =IFERROR(SUMIFS(Raw_IFRS17!$C:$C,Raw_IFRS17!$F:$F,$I14,Raw_IFRS17!$G:$G,"Y"),0) | D14: =IFERROR(SUMIFS(Raw_IFRS17!$D:$D,Raw_IFRS17!$F:$F,$I14,Raw_IFRS17!$G:$G,"Y"),0) | E14: =IFERROR(SUMIFS(Raw_IFRS17!$E:$E,Raw_IFRS17!$F:$F,$I14,Raw_IFRS17!$G:$G,"Y"),0) | F14: =IFERROR((C14/D14)-1,"") | H14: =IF(OR(C14=0,C14=""),"Review / optional","OK") | I14: I17_REINS_ASSET
A15: Posisi keuangan | B15: Reinsurance contract liabilities | C15: =IFERROR(SUMIFS(Raw_IFRS17!$C:$C,Raw_IFRS17!$F:$F,$I15,Raw_IFRS17!$G:$G,"Y"),0) | D15: =IFERROR(SUMIFS(Raw_IFRS17!$D:$D,Raw_IFRS17!$F:$F,$I15,Raw_IFRS17!$G:$G,"Y"),0) | E15: =IFERROR(SUMIFS(Raw_IFRS17!$E:$E,Raw_IFRS17!$F:$F,$I15,Raw_IFRS17!$G:$G,"Y"),0) | F15: =IFERROR((C15/D15)-1,"") | H15: =IF(OR(C15=0,C15=""),"Review / optional","OK") | I15: I17_REINS_LIAB
A16: Posisi keuangan | B16: Liability for remaining coverage (LRC) excl. loss component | C16: =IFERROR(SUMIFS(Raw_IFRS17!$C:$C,Raw_IFRS17!$F:$F,$I16,Raw_IFRS17!$G:$G,"Y"),0) | D16: =IFERROR(SUMIFS(Raw_IFRS17!$D:$D,Raw_IFRS17!$F:$F,$I16,Raw_IFRS17!$G:$G,"Y"),0) | E16: =IFERROR(SUMIFS(Raw_IFRS17!$E:$E,Raw_IFRS17!$F:$F,$I16,Raw_IFRS17!$G:$G,"Y"),0) | F16: =IFERROR((C16/D16)-1,"") | H16: =IF(OR(C16=0,C16=""),"Review / optional","OK") | I16: I17_LRC
A17: Posisi keuangan | B17: Liability for incurred claims (LIC) | C17: =IFERROR(SUMIFS(Raw_IFRS17!$C:$C,Raw_IFRS17!$F:$F,$I17,Raw_IFRS17!$G:$G,"Y"),0) | D17: =IFERROR(SUMIFS(Raw_IFRS17!$D:$D,Raw_IFRS17!$F:$F,$I17,Raw_IFRS17!$G:$G,"Y"),0) | E17: =IFERROR(SUMIFS(Raw_IFRS17!$E:$E,Raw_IFRS17!$F:$F,$I17,Raw_IFRS17!$G:$G,"Y"),0) | F17: =IFERROR((C17/D17)-1,"") | H17: =IF(OR(C17=0,C17=""),"Review / optional","OK") | I17: I17_LIC
A18: Posisi keuangan | B18: Loss component | C18: =IFERROR(SUMIFS(Raw_IFRS17!$C:$C,Raw_IFRS17!$F:$F,$I18,Raw_IFRS17!$G:$G,"Y"),0) | D18: =IFERROR(SUMIFS(Raw_IFRS17!$D:$D,Raw_IFRS17!$F:$F,$I18,Raw_IFRS17!$G:$G,"Y"),0) | E18: =IFERROR(SUMIFS(Raw_IFRS17!$E:$E,Raw_IFRS17!$F:$F,$I18,Raw_IFRS17!$G:$G,"Y"),0) | F18: =IFERROR((C18/D18)-1,"") | H18: =IF(OR(C18=0,C18=""),"Review / optional","OK") | I18: I17_LOSSCOMP
A19: Posisi keuangan | B19: Risk adjustment for non-financial risk | C19: =IFERROR(SUMIFS(Raw_IFRS17!$C:$C,Raw_IFRS17!$F:$F,$I19,Raw_IFRS17!$G:$G,"Y"),0) | D19: =IFERROR(SUMIFS(Raw_IFRS17!$D:$D,Raw_IFRS17!$F:$F,$I19,Raw_IFRS17!$G:$G,"Y"),0) | E19: =IFERROR(SUMIFS(Raw_IFRS17!$E:$E,Raw_IFRS17!$F:$F,$I19,Raw_IFRS17!$G:$G,"Y"),0) | F19: =IFERROR((C19/D19)-1,"") | H19: =IF(OR(C19=0,C19=""),"Review / optional","OK") | I19: I17_RA
A20: CSM | B20: Opening CSM | C20: =IFERROR(SUMIFS(Raw_IFRS17!$C:$C,Raw_IFRS17!$F:$F,$I20,Raw_IFRS17!$G:$G,"Y"),0) | D20: =IFERROR(SUMIFS(Raw_IFRS17!$D:$D,Raw_IFRS17!$F:$F,$I20,Raw_IFRS17!$G:$G,"Y"),0) | E20: =IFERROR(SUMIFS(Raw_IFRS17!$E:$E,Raw_IFRS17!$F:$F,$I20,Raw_IFRS17!$G:$G,"Y"),0) | F20: =IFERROR((C20/D20)-1,"") | H20: =IF(OR(C20=0,C20=""),"Review / optional","OK") | I20: I17_CSM_OPEN
A21: CSM | B21: New business / contracts issued | C21: =IFERROR(SUMIFS(Raw_IFRS17!$C:$C,Raw_IFRS17!$F:$F,$I21,Raw_IFRS17!$G:$G,"Y"),0) | D21: =IFERROR(SUMIFS(Raw_IFRS17!$D:$D,Raw_IFRS17!$F:$F,$I21,Raw_IFRS17!$G:$G,"Y"),0) | E21: =IFERROR(SUMIFS(Raw_IFRS17!$E:$E,Raw_IFRS17!$F:$F,$I21,Raw_IFRS17!$G:$G,"Y"),0) | F21: =IFERROR((C21/D21)-1,"") | H21: =IF(OR(C21=0,C21=""),"Review / optional","OK") | I21: I17_CSM_NEW
A22: CSM | B22: Interest accretion on CSM | C22: =IFERROR(SUMIFS(Raw_IFRS17!$C:$C,Raw_IFRS17!$F:$F,$I22,Raw_IFRS17!$G:$G,"Y"),0) | D22: =IFERROR(SUMIFS(Raw_IFRS17!$D:$D,Raw_IFRS17!$F:$F,$I22,Raw_IFRS17!$G:$G,"Y"),0) | E22: =IFERROR(SUMIFS(Raw_IFRS17!$E:$E,Raw_IFRS17!$F:$F,$I22,Raw_IFRS17!$G:$G,"Y"),0) | F22: =IFERROR((C22/D22)-1,"") | H22: =IF(OR(C22=0,C22=""),"Review / optional","OK") | I22: I17_CSM_ACC
A23: CSM | B23: Changes related to future service | C23: =IFERROR(SUMIFS(Raw_IFRS17!$C:$C,Raw_IFRS17!$F:$F,$I23,Raw_IFRS17!$G:$G,"Y"),0) | D23: =IFERROR(SUMIFS(Raw_IFRS17!$D:$D,Raw_IFRS17!$F:$F,$I23,Raw_IFRS17!$G:$G,"Y"),0) | E23: =IFERROR(SUMIFS(Raw_IFRS17!$E:$E,Raw_IFRS17!$F:$F,$I23,Raw_IFRS17!$G:$G,"Y"),0) | F23: =IFERROR((C23/D23)-1,"") | H23: =IF(OR(C23=0,C23=""),"Review / optional","OK") | I23: I17_CSM_FUT
A24: CSM | B24: CSM recognised for services provided | C24: =IFERROR(SUMIFS(Raw_IFRS17!$C:$C,Raw_IFRS17!$F:$F,$I24,Raw_IFRS17!$G:$G,"Y"),0) | D24: =IFERROR(SUMIFS(Raw_IFRS17!$D:$D,Raw_IFRS17!$F:$F,$I24,Raw_IFRS17!$G:$G,"Y"),0) | E24: =IFERROR(SUMIFS(Raw_IFRS17!$E:$E,Raw_IFRS17!$F:$F,$I24,Raw_IFRS17!$G:$G,"Y"),0) | F24: =IFERROR((C24/D24)-1,"") | H24: =IF(OR(C24=0,C24=""),"Review / optional","OK") | I24: I17_CSM_SERV
A25: CSM | B25: FX and other movements | C25: =IFERROR(SUMIFS(Raw_IFRS17!$C:$C,Raw_IFRS17!$F:$F,$I25,Raw_IFRS17!$G:$G,"Y"),0) | D25: =IFERROR(SUMIFS(Raw_IFRS17!$D:$D,Raw_IFRS17!$F:$F,$I25,Raw_IFRS17!$G:$G,"Y"),0) | E25: =IFERROR(SUMIFS(Raw_IFRS17!$E:$E,Raw_IFRS17!$F:$F,$I25,Raw_IFRS17!$G:$G,"Y"),0) | F25: =IFERROR((C25/D25)-1,"") | H25: =IF(OR(C25=0,C25=""),"Review / optional","OK") | I25: I17_CSM_OTHER
A26: CSM | B26: CLOSING CSM | C26: =IF(SUM(C20:C25)=0,"",C20+C21+C22+C23-C24+C25) | D26: =IF(SUM(D20:D25)=0,"",D20+D21+D22+D23-D24+D25) | E26: =IF(SUM(E20:E25)=0,"",E20+E21+E22+E23-E24+E25) | F26: =IFERROR((C26/D26)-1,"") | G26: V5: closing CSM = opening + new + interest + future service changes - CSM recognised + other.
A27: Operasional | B27: Insurance acquisition cash flow asset | C27: =IFERROR(SUMIFS(Raw_IFRS17!$C:$C,Raw_IFRS17!$F:$F,$I27,Raw_IFRS17!$G:$G,"Y"),0) | D27: =IFERROR(SUMIFS(Raw_IFRS17!$D:$D,Raw_IFRS17!$F:$F,$I27,Raw_IFRS17!$G:$G,"Y"),0) | E27: =IFERROR(SUMIFS(Raw_IFRS17!$E:$E,Raw_IFRS17!$F:$F,$I27,Raw_IFRS17!$G:$G,"Y"),0) | F27: =IFERROR((C27/D27)-1,"") | H27: =IF(OR(C27=0,C27=""),"Review / optional","OK") | I27: I17_ACQASSET
A28: Operasional | B28: Policies in force / coverage units | C28: =IFERROR(SUMIFS(Raw_IFRS17!$C:$C,Raw_IFRS17!$F:$F,$I28,Raw_IFRS17!$G:$G,"Y"),0) | D28: =IFERROR(SUMIFS(Raw_IFRS17!$D:$D,Raw_IFRS17!$F:$F,$I28,Raw_IFRS17!$G:$G,"Y"),0) | E28: =IFERROR(SUMIFS(Raw_IFRS17!$E:$E,Raw_IFRS17!$F:$F,$I28,Raw_IFRS17!$G:$G,"Y"),0) | F28: =IFERROR((C28/D28)-1,"") | H28: =IF(OR(C28=0,C28=""),"Review / optional","OK") | I28: I17_COV_UNITS
A29: Operasional | B29: New business APE / new premiums | C29: =IFERROR(SUMIFS(Raw_IFRS17!$C:$C,Raw_IFRS17!$F:$F,$I29,Raw_IFRS17!$G:$G,"Y"),0) | D29: =IFERROR(SUMIFS(Raw_IFRS17!$D:$D,Raw_IFRS17!$F:$F,$I29,Raw_IFRS17!$G:$G,"Y"),0) | E29: =IFERROR(SUMIFS(Raw_IFRS17!$E:$E,Raw_IFRS17!$F:$F,$I29,Raw_IFRS17!$G:$G,"Y"),0) | F29: =IFERROR((C29/D29)-1,"") | H29: =IF(OR(C29=0,C29=""),"Review / optional","OK") | I29: I17_NEWBUS
A30: Operasional | B30: Claim ratio (if disclosed) | C30: =IFERROR(SUMIFS(Raw_IFRS17!$C:$C,Raw_IFRS17!$F:$F,$I30,Raw_IFRS17!$G:$G,"Y"),0) | D30: =IFERROR(SUMIFS(Raw_IFRS17!$D:$D,Raw_IFRS17!$F:$F,$I30,Raw_IFRS17!$G:$G,"Y"),0) | E30: =IFERROR(SUMIFS(Raw_IFRS17!$E:$E,Raw_IFRS17!$F:$F,$I30,Raw_IFRS17!$G:$G,"Y"),0) | F30: =IFERROR((C30/D30)-1,"") | H30: =IF(OR(C30=0,C30=""),"Review / optional","OK") | I30: I17_CLAIM_RATIO
A31: Operasional | B31: Reinsurance cession ratio (if disclosed) | C31: =IF(COUNTIFS(Raw_IFRS17!$F:$F,$I31,Raw_IFRS17!$G:$G,"Y")>0,SUMIFS(Raw_IFRS17!$C:$C,Raw_IFRS17!$F:$F,$I31,Raw_IFRS17!$G:$G,"Y"),IFERROR(C14/C13,0)) | D31: =IF(COUNTIFS(Raw_IFRS17!$F:$F,$I31,Raw_IFRS17!$G:$G,"Y")>0,SUMIFS(Raw_IFRS17!$D:$D,Raw_IFRS17!$F:$F,$I31,Raw_IFRS17!$G:$G,"Y"),IFERROR(D14/D13,0)) | E31: =IF(COUNTIFS(Raw_IFRS17!$F:$F,$I31,Raw_IFRS17!$G:$G,"Y")>0,SUMIFS(Raw_IFRS17!$E:$E,Raw_IFRS17!$F:$F,$I31,Raw_IFRS17!$G:$G,"Y"),IFERROR(E14/E13,0)) | F31: =IFERROR((C31/D31)-1,"") | H31: =IF(OR(C31=0,C31=""),"Review / optional","OK") | I31: I17_CESSION
A32: Operasional | B32: Discount rate / locked-in rate (avg) | C32: =IF(C29<>"",C29,IFERROR(ABS(C4)/C3,"")) | D32: =IF(D29<>"",D29,IFERROR(ABS(D4)/D3,"")) | E32: =IF(E29<>"",E29,IFERROR(ABS(E4)/E3,"")) | F32: =IFERROR((C32/D32)-1,"") | H32: =IF(OR(C32=0,C32=""),"Review / optional","OK") | I32: I17_DISC_RATE
A33: Rasio bantu | B33: CSM / equity | C33: =IFERROR(IF(Input_SFP!C34>0,C26/Input_SFP!C34,""),"") | D33: =IFERROR(IF(Input_SFP!D34>0,D26/Input_SFP!D34,""),"") | E33: =IFERROR(IF(Input_SFP!E34>0,E26/Input_SFP!E34,""),"") | F33: =IFERROR((C33/D33)-1,"")
A34: Rasio bantu | B34: Claim ratio (derived if blank) | C34: =IFERROR(IF(C30>0,C30,IF(C3>0,ABS(C4)/ABS(C3),"")),"") | D34: =IFERROR(IF(D30>0,D30,IF(D3>0,ABS(D4)/ABS(D3),"")),"") | E34: =IFERROR(IF(E30>0,E30,IF(E3>0,ABS(E4)/ABS(E3),"")),"") | F34: =IFERROR((C34/D34)-1,"")

Sheet Input_IFRS9_Detail
A1: INPUT DETAIL IFRS 9 / PSAK 109
A2: Kelompok | B2: Akun standar | C2: CY | D2: PY | E2: PPY | F2: Growth vs PY | G2: Ratio / note | H2: Status | I2: Mapping code
A3: Aset keuangan | B3: FVTPL carrying amount | C3: =IFERROR(SUMIFS(Raw_IFRS9!$C:$C,Raw_IFRS9!$F:$F,$I3,Raw_IFRS9!$G:$G,"Y"),0) | D3: =IFERROR(SUMIFS(Raw_IFRS9!$D:$D,Raw_IFRS9!$F:$F,$I3,Raw_IFRS9!$G:$G,"Y"),0) | E3: =IFERROR(SUMIFS(Raw_IFRS9!$E:$E,Raw_IFRS9!$F:$F,$I3,Raw_IFRS9!$G:$G,"Y"),0) | F3: =IFERROR((C3/D3)-1,"") | H3: =IF(OR(C3=0,C3=""),"Review / optional","OK") | I3: I9_FVTPL
A4: Aset keuangan | B4: FVOCI debt instruments carrying amount | C4: =IFERROR(SUMIFS(Raw_IFRS9!$C:$C,Raw_IFRS9!$F:$F,$I4,Raw_IFRS9!$G:$G,"Y"),0) | D4: =IFERROR(SUMIFS(Raw_IFRS9!$D:$D,Raw_IFRS9!$F:$F,$I4,Raw_IFRS9!$G:$G,"Y"),0) | E4: =IFERROR(SUMIFS(Raw_IFRS9!$E:$E,Raw_IFRS9!$F:$F,$I4,Raw_IFRS9!$G:$G,"Y"),0) | F4: =IFERROR((C4/D4)-1,"") | H4: =IF(OR(C4=0,C4=""),"Review / optional","OK") | I4: I9_FVOCI_DEBT
A5: Aset keuangan | B5: FVOCI equity instruments carrying amount | C5: =IFERROR(SUMIFS(Raw_IFRS9!$C:$C,Raw_IFRS9!$F:$F,$I5,Raw_IFRS9!$G:$G,"Y"),0) | D5: =IFERROR(SUMIFS(Raw_IFRS9!$D:$D,Raw_IFRS9!$F:$F,$I5,Raw_IFRS9!$G:$G,"Y"),0) | E5: =IFERROR(SUMIFS(Raw_IFRS9!$E:$E,Raw_IFRS9!$F:$F,$I5,Raw_IFRS9!$G:$G,"Y"),0) | F5: =IFERROR((C5/D5)-1,"") | H5: =IF(OR(C5=0,C5=""),"Review / optional","OK") | I5: I9_FVOCI_EQ
A6: Aset keuangan | B6: Amortised cost debt instruments carrying amount | C6: =IFERROR(SUMIFS(Raw_IFRS9!$C:$C,Raw_IFRS9!$F:$F,$I6,Raw_IFRS9!$G:$G,"Y"),0) | D6: =IFERROR(SUMIFS(Raw_IFRS9!$D:$D,Raw_IFRS9!$F:$F,$I6,Raw_IFRS9!$G:$G,"Y"),0) | E6: =IFERROR(SUMIFS(Raw_IFRS9!$E:$E,Raw_IFRS9!$F:$F,$I6,Raw_IFRS9!$G:$G,"Y"),0) | F6: =IFERROR((C6/D6)-1,"") | H6: =IF(OR(C6=0,C6=""),"Review / optional","OK") | I6: I9_AC_DEBT
A7: Aset keuangan | B7: Loans and receivables carrying amount | C7: =IFERROR(SUMIFS(Raw_IFRS9!$C:$C,Raw_IFRS9!$F:$F,$I7,Raw_IFRS9!$G:$G,"Y"),0) | D7: =IFERROR(SUMIFS(Raw_IFRS9!$D:$D,Raw_IFRS9!$F:$F,$I7,Raw_IFRS9!$G:$G,"Y"),0) | E7: =IFERROR(SUMIFS(Raw_IFRS9!$E:$E,Raw_IFRS9!$F:$F,$I7,Raw_IFRS9!$G:$G,"Y"),0) | F7: =IFERROR((C7/D7)-1,"") | H7: =IF(OR(C7=0,C7=""),"Review / optional","OK") | I7: I9_LOANS
A8: ECL | B8: TOTAL financial assets subject to ECL | C8: =SUM(C9:C11) | D8: =SUM(D9:D11) | E8: =SUM(E9:E11) | F8: =IFERROR((C8/D8)-1,"")
A9: ECL | B9: Stage 1 gross exposure | C9: =IFERROR(SUMIFS(Raw_IFRS9!$C:$C,Raw_IFRS9!$F:$F,$I9,Raw_IFRS9!$G:$G,"Y"),0) | D9: =IFERROR(SUMIFS(Raw_IFRS9!$D:$D,Raw_IFRS9!$F:$F,$I9,Raw_IFRS9!$G:$G,"Y"),0) | E9: =IFERROR(SUMIFS(Raw_IFRS9!$E:$E,Raw_IFRS9!$F:$F,$I9,Raw_IFRS9!$G:$G,"Y"),0) | F9: =IFERROR((C9/D9)-1,"") | H9: =IF(OR(C9=0,C9=""),"Review / optional","OK") | I9: I9_STAGE1_EXP
A10: ECL | B10: Stage 2 gross exposure | C10: =IFERROR(SUMIFS(Raw_IFRS9!$C:$C,Raw_IFRS9!$F:$F,$I10,Raw_IFRS9!$G:$G,"Y"),0) | D10: =IFERROR(SUMIFS(Raw_IFRS9!$D:$D,Raw_IFRS9!$F:$F,$I10,Raw_IFRS9!$G:$G,"Y"),0) | E10: =IFERROR(SUMIFS(Raw_IFRS9!$E:$E,Raw_IFRS9!$F:$F,$I10,Raw_IFRS9!$G:$G,"Y"),0) | F10: =IFERROR((C10/D10)-1,"") | H10: =IF(OR(C10=0,C10=""),"Review / optional","OK") | I10: I9_STAGE2_EXP
A11: ECL | B11: Stage 3 gross exposure | C11: =IFERROR(SUMIFS(Raw_IFRS9!$C:$C,Raw_IFRS9!$F:$F,$I11,Raw_IFRS9!$G:$G,"Y"),0) | D11: =IFERROR(SUMIFS(Raw_IFRS9!$D:$D,Raw_IFRS9!$F:$F,$I11,Raw_IFRS9!$G:$G,"Y"),0) | E11: =IFERROR(SUMIFS(Raw_IFRS9!$E:$E,Raw_IFRS9!$F:$F,$I11,Raw_IFRS9!$G:$G,"Y"),0) | F11: =IFERROR((C11/D11)-1,"") | H11: =IF(OR(C11=0,C11=""),"Review / optional","OK") | I11: I9_STAGE3_EXP
A12: ECL | B12: Stage 1 allowance | C12: =IFERROR(SUMIFS(Raw_IFRS9!$C:$C,Raw_IFRS9!$F:$F,$I12,Raw_IFRS9!$G:$G,"Y"),0) | D12: =IFERROR(SUMIFS(Raw_IFRS9!$D:$D,Raw_IFRS9!$F:$F,$I12,Raw_IFRS9!$G:$G,"Y"),0) | E12: =IFERROR(SUMIFS(Raw_IFRS9!$E:$E,Raw_IFRS9!$F:$F,$I12,Raw_IFRS9!$G:$G,"Y"),0) | F12: =IFERROR((C12/D12)-1,"") | H12: =IF(OR(C12=0,C12=""),"Review / optional","OK") | I12: I9_STAGE1_ALL
A13: ECL | B13: Stage 2 allowance | C13: =IFERROR(SUMIFS(Raw_IFRS9!$C:$C,Raw_IFRS9!$F:$F,$I13,Raw_IFRS9!$G:$G,"Y"),0) | D13: =IFERROR(SUMIFS(Raw_IFRS9!$D:$D,Raw_IFRS9!$F:$F,$I13,Raw_IFRS9!$G:$G,"Y"),0) | E13: =IFERROR(SUMIFS(Raw_IFRS9!$E:$E,Raw_IFRS9!$F:$F,$I13,Raw_IFRS9!$G:$G,"Y"),0) | F13: =IFERROR((C13/D13)-1,"") | H13: =IF(OR(C13=0,C13=""),"Review / optional","OK") | I13: I9_STAGE2_ALL
A14: ECL | B14: Stage 3 allowance | C14: =IFERROR(SUMIFS(Raw_IFRS9!$C:$C,Raw_IFRS9!$F:$F,$I14,Raw_IFRS9!$G:$G,"Y"),0) | D14: =IFERROR(SUMIFS(Raw_IFRS9!$D:$D,Raw_IFRS9!$F:$F,$I14,Raw_IFRS9!$G:$G,"Y"),0) | E14: =IFERROR(SUMIFS(Raw_IFRS9!$E:$E,Raw_IFRS9!$F:$F,$I14,Raw_IFRS9!$G:$G,"Y"),0) | F14: =IFERROR((C14/D14)-1,"") | H14: =IF(OR(C14=0,C14=""),"Review / optional","OK") | I14: I9_STAGE3_ALL
A15: ECL | B15: TOTAL allowance ECL | C15: =SUM(C12:C14) | D15: =SUM(D12:D14) | E15: =SUM(E12:E14) | F15: =IFERROR((C15/D15)-1,"")
A16: ECL | B16: Coverage on ECL assets | C16: =IFERROR(IF(C8>0,C15/C8,""),"") | D16: =IFERROR(IF(D8>0,D15/D8,""),"") | E16: =IFERROR(IF(E8>0,E15/E8,""),"") | F16: =IFERROR((C16/D16)-1,"")
A17: Kualitas aset | B17: Low credit risk exposure | C17: =IFERROR(SUMIFS(Raw_IFRS9!$C:$C,Raw_IFRS9!$F:$F,$I17,Raw_IFRS9!$G:$G,"Y"),0) | D17: =IFERROR(SUMIFS(Raw_IFRS9!$D:$D,Raw_IFRS9!$F:$F,$I17,Raw_IFRS9!$G:$G,"Y"),0) | E17: =IFERROR(SUMIFS(Raw_IFRS9!$E:$E,Raw_IFRS9!$F:$F,$I17,Raw_IFRS9!$G:$G,"Y"),0) | F17: =IFERROR((C17/D17)-1,"") | H17: =IF(OR(C17=0,C17=""),"Review / optional","OK") | I17: I9_LOWRISK
A18: Kualitas aset | B18: Credit-impaired exposure | C18: =IFERROR(SUMIFS(Raw_IFRS9!$C:$C,Raw_IFRS9!$F:$F,$I18,Raw_IFRS9!$G:$G,"Y"),0) | D18: =IFERROR(SUMIFS(Raw_IFRS9!$D:$D,Raw_IFRS9!$F:$F,$I18,Raw_IFRS9!$G:$G,"Y"),0) | E18: =IFERROR(SUMIFS(Raw_IFRS9!$E:$E,Raw_IFRS9!$F:$F,$I18,Raw_IFRS9!$G:$G,"Y"),0) | F18: =IFERROR((C18/D18)-1,"") | H18: =IF(OR(C18=0,C18=""),"Review / optional","OK") | I18: I9_CREDIT_IMP
A19: Kualitas aset | B19: Write-offs during year | C19: =IFERROR(SUMIFS(Raw_IFRS9!$C:$C,Raw_IFRS9!$F:$F,$I19,Raw_IFRS9!$G:$G,"Y"),0) | D19: =IFERROR(SUMIFS(Raw_IFRS9!$D:$D,Raw_IFRS9!$F:$F,$I19,Raw_IFRS9!$G:$G,"Y"),0) | E19: =IFERROR(SUMIFS(Raw_IFRS9!$E:$E,Raw_IFRS9!$F:$F,$I19,Raw_IFRS9!$G:$G,"Y"),0) | F19: =IFERROR((C19/D19)-1,"") | H19: =IF(OR(C19=0,C19=""),"Review / optional","OK") | I19: I9_WRITEOFF
A20: Kualitas aset | B20: Recovery of written-off assets | C20: =IFERROR(SUMIFS(Raw_IFRS9!$C:$C,Raw_IFRS9!$F:$F,$I20,Raw_IFRS9!$G:$G,"Y"),0) | D20: =IFERROR(SUMIFS(Raw_IFRS9!$D:$D,Raw_IFRS9!$F:$F,$I20,Raw_IFRS9!$G:$G,"Y"),0) | E20: =IFERROR(SUMIFS(Raw_IFRS9!$E:$E,Raw_IFRS9!$F:$F,$I20,Raw_IFRS9!$G:$G,"Y"),0) | F20: =IFERROR((C20/D20)-1,"") | H20: =IF(OR(C20=0,C20=""),"Review / optional","OK") | I20: I9_RECOVERY
A21: OCI | B21: FVOCI reserve closing | C21: =IFERROR(SUMIFS(Raw_IFRS9!$C:$C,Raw_IFRS9!$F:$F,$I21,Raw_IFRS9!$G:$G,"Y"),0) | D21: =IFERROR(SUMIFS(Raw_IFRS9!$D:$D,Raw_IFRS9!$F:$F,$I21,Raw_IFRS9!$G:$G,"Y"),0) | E21: =IFERROR(SUMIFS(Raw_IFRS9!$E:$E,Raw_IFRS9!$F:$F,$I21,Raw_IFRS9!$G:$G,"Y"),0) | F21: =IFERROR((C21/D21)-1,"") | H21: =IF(OR(C21=0,C21=""),"Review / optional","OK") | I21: I9_FVOCI_RES
A22: P/L | B22: Fair value gain/(loss) on FVTPL recognised in P/L | C22: =IFERROR(SUMIFS(Raw_IFRS9!$C:$C,Raw_IFRS9!$F:$F,$I22,Raw_IFRS9!$G:$G,"Y"),0) | D22: =IFERROR(SUMIFS(Raw_IFRS9!$D:$D,Raw_IFRS9!$F:$F,$I22,Raw_IFRS9!$G:$G,"Y"),0) | E22: =IFERROR(SUMIFS(Raw_IFRS9!$E:$E,Raw_IFRS9!$F:$F,$I22,Raw_IFRS9!$G:$G,"Y"),0) | F22: =IFERROR((C22/D22)-1,"") | H22: =IF(OR(C22=0,C22=""),"Review / optional","OK") | I22: I9_FVTPL_PL
A23: P/L | B23: Investment income on financial assets | C23: =IFERROR(SUMIFS(Raw_IFRS9!$C:$C,Raw_IFRS9!$F:$F,$I23,Raw_IFRS9!$G:$G,"Y"),0) | D23: =IFERROR(SUMIFS(Raw_IFRS9!$D:$D,Raw_IFRS9!$F:$F,$I23,Raw_IFRS9!$G:$G,"Y"),0) | E23: =IFERROR(SUMIFS(Raw_IFRS9!$E:$E,Raw_IFRS9!$F:$F,$I23,Raw_IFRS9!$G:$G,"Y"),0) | F23: =IFERROR((C23/D23)-1,"") | H23: =IF(OR(C23=0,C23=""),"Review / optional","OK") | I23: I9_INV_INC
A24: P/L | B24: Average investment assets | C24: =IFERROR(SUMIFS(Raw_IFRS9!$C:$C,Raw_IFRS9!$F:$F,$I24,Raw_IFRS9!$G:$G,"Y"),0) | D24: =IFERROR(SUMIFS(Raw_IFRS9!$D:$D,Raw_IFRS9!$F:$F,$I24,Raw_IFRS9!$G:$G,"Y"),0) | E24: =IFERROR(SUMIFS(Raw_IFRS9!$E:$E,Raw_IFRS9!$F:$F,$I24,Raw_IFRS9!$G:$G,"Y"),0) | F24: =IFERROR((C24/D24)-1,"") | H24: =IF(OR(C24=0,C24=""),"Review / optional","OK") | I24: I9_AVG_INV
A25: P/L | B25: Portfolio yield | C25: =IFERROR(IF(C24>0,C23/C24,""),"") | D25: =IFERROR(IF(D24>0,D23/D24,""),"") | E25: =IFERROR(IF(E24>0,E23/E24,""),"") | F25: =IFERROR((C25/D25)-1,"")
A26: Sensitivitas | B26: Interest rate duration / sensitivity (years) | C26: =IFERROR(SUMIFS(Raw_IFRS9!$C:$C,Raw_IFRS9!$F:$F,$I26,Raw_IFRS9!$G:$G,"Y"),0) | D26: =IFERROR(SUMIFS(Raw_IFRS9!$D:$D,Raw_IFRS9!$F:$F,$I26,Raw_IFRS9!$G:$G,"Y"),0) | E26: =IFERROR(SUMIFS(Raw_IFRS9!$E:$E,Raw_IFRS9!$F:$F,$I26,Raw_IFRS9!$G:$G,"Y"),0) | F26: =IFERROR((C26/D26)-1,"") | H26: =IF(OR(C26=0,C26=""),"Review / optional","OK") | I26: I9_DURATION

Sheet Mapping_Akun
A1: MAPPING CODE REFERENCE
A2: Code | B2: Summary sheet | C2: Meaning | D2: Typical audited line items | E2: Comment
A3: SFP_CASH | B3: Input_SFP | C3: Kas dan setara kas | D3: ASET
A4: SFP_MM | B4: Input_SFP | C4: Penempatan jangka pendek / pasar uang | D4: ASET
A5: SFP_FVTPL | B5: Input_SFP | C5: Investasi pada FVTPL | D5: ASET
A6: SFP_FVOCI_DEBT | B6: Input_SFP | C6: Investasi utang pada FVOCI | D6: ASET
A7: SFP_FVOCI_EQ | B7: Input_SFP | C7: Investasi ekuitas pada FVOCI | D7: ASET
A8: SFP_AC | B8: Input_SFP | C8: Investasi pada biaya perolehan diamortisasi | D8: ASET
A9: SFP_INVPROP | B9: Input_SFP | C9: Properti investasi | D9: ASET
A10: SFP_LOANS | B10: Input_SFP | C10: Pinjaman polis / piutang pembiayaan / loans | D10: ASET
A11: SFP_RECEIV | B11: Input_SFP | C11: Piutang premi dan piutang lain-lain | D11: ASET
A12: SFP_REINS_ASSET | B12: Input_SFP | C12: Aset kontrak reasuransi | D12: ASET
A13: SFP_ACQASSET | B13: Input_SFP | C13: Aset akuisisi asuransi / acquisition cash flow asset | D13: ASET
A14: SFP_PPE | B14: Input_SFP | C14: Aset tetap, ROU, dan properti yang digunakan sendiri | D14: ASET
... A97: CF_BEGIN | B97: Input_CF | C97: Opening cash | D97: Cash flow
A98: DETAIL_ONLY | B98: RAW sheets only | C98: Stored for reference, excluded from summary | D98: Any audited line item | E98: Use G='N' or code DETAIL_ONLY

Sheet Rasio
A1: RASIO KEUANGAN OTOMATIS – ASURANSI JIWA
A2: Kategori | B2: Rasio | C2: CY | D2: PY | E2: PPY | F2: Threshold / target | G2: Status | H2: Catatan
A3: Profitabilitas | B3: ROA | C3: =IFERROR(Input_PL_OCI!C16/Input_SFP!C18,"") | D3: =IFERROR(Input_PL_OCI!D16/Input_SFP!D18,"") | E3: =IFERROR(Input_PL_OCI!E16/Input_SFP!E18,"") | F3: >=Setup!B15 | G3: =IF(OR(C3="",ISBLANK(C3)),"NO DATA",IF(C3>=Setup!B15,"OK","Perlu perhatian"))
A4: Profitabilitas | B4: ROE | C4: =IFERROR(Input_PL_OCI!C16/Input_SFP!C34,"") | D4: =IFERROR(Input_PL_OCI!D16/Input_SFP!D34,"") | E4: =IFERROR(Input_PL_OCI!E16/Input_SFP!E34,"") | F4: >=Setup!B16 | G4: =IF(OR(C4="",ISBLANK(C4)),"NO DATA",IF(C4>=Setup!B16,"OK","Perlu perhatian"))
A5: Leverage | B5: Liabilities / Equity | C5: =IFERROR(Input_SFP!C26/Input_SFP!C34,"") | D5: =IFERROR(Input_SFP!D26/Input_SFP!D34,"") | E5: =IFERROR(Input_SFP!E26/Input_SFP!E34,"") | F5: <=Setup!B14 | G5: =IF(OR(C5="",ISBLANK(C5)),"NO DATA",IF(C5<=Setup!B14,"OK","Perlu perhatian"))
A6: Likuiditas | B6: Cash / Liabilities | C6: =IFERROR(Input_SFP!C3/Input_SFP!C26,"") | D6: =IFERROR(Input_SFP!D3/Input_SFP!D26,"") | E6: =IFERROR(Input_SFP!E3/Input_SFP!E26,"") | F6: >=Setup!B13 | G6: =IF(OR(C6="",ISBLANK(C6)),"NO DATA",IF(C6>=Setup!B13,"OK","Perlu perhatian"))
A7: IFRS17 | B7: Claim ratio | C7: =IFERROR(Input_IFRS17_Detail!C34,"") | D7: =IFERROR(Input_IFRS17_Detail!D34,"") | E7: =IFERROR(Input_IFRS17_Detail!E34,"") | F7: <=Setup!B17 | G7: =IF(OR(C7="",ISBLANK(C7)),"NO DATA",IF(C7<=Setup!B17,"OK","Perlu perhatian"))
A8: IFRS17 | B8: CSM / Equity | C8: =IFERROR(Input_IFRS17_Detail!C33,"") | D8: =IFERROR(Input_IFRS17_Detail!D33,"") | E8: =IFERROR(Input_IFRS17_Detail!E33,"") | F8: >=Setup!B25 | G8: =IF(OR(C8="",ISBLANK(C8)),"NO DATA",IF(C8>=Setup!B25,"OK","Perlu perhatian"))
A9: IFRS17 | B9: Reinsurance cession ratio | C9: =IFERROR(Input_IFRS17_Detail!C31,"") | D9: =IFERROR(Input_IFRS17_Detail!D31,"") | E9: =IFERROR(Input_IFRS17_Detail!E31,"") | F9: <=Setup!B27 | G9: =IF(OR(C9="",ISBLANK(C9)),"NO DATA",IF(C9<=Setup!B27,"OK","Perlu perhatian"))
A10: IFRS9 | B10: ECL coverage | C10: =IFERROR(Input_IFRS9_Detail!C16,"") | D10: =IFERROR(Input_IFRS9_Detail!D16,"") | E10: =IFERROR(Input_IFRS9_Detail!E16,"") | F10: >=Setup!B21 | G10: =IF(OR(C10="",ISBLANK(C10)),"NO DATA",IF(C10>=Setup!B21,"OK","Perlu perhatian"))
A11: IFRS9 | B11: Stage 2+3 ratio | C11: =IFERROR((Input_IFRS9_Detail!C10+Input_IFRS9_Detail!C11)/Input_IFRS9_Detail!C8,"") | D11: =IFERROR((Input_IFRS9_Detail!D10+Input_IFRS9_Detail!D11)/Input_IFRS9_Detail!D8,"") | E11: =IFERROR((Input_IFRS9_Detail!E10+Input_IFRS9_Detail!E11)/Input_IFRS9_Detail!E8,"") | F11: <=Setup!B22 | G11: =IF(OR(C11="",ISBLANK(C11)),"NO DATA",IF(C11<=Setup!B22,"OK","Perlu perhatian"))
A12: Arus kas | B12: OCF / Profit | C12: =IFERROR(Input_CF!C3/Input_PL_OCI!C16,"") | D12: =IFERROR(Input_CF!D3/Input_PL_OCI!D16,"") | E12: =IFERROR(Input_CF!E3/Input_PL_OCI!E16,"") | F12: >=Setup!B23 | G12: =IF(OR(C12="",ISBLANK(C12)),"NO DATA",IF(C12>=Setup!B23,"OK","Perlu perhatian"))
A13: Arus kas | B13: Ending cash vs SFP cash | C13: =IFERROR(Input_CF!C9/Input_SFP!C3,"") | D13: =IFERROR(Input_CF!D9/Input_SFP!D3,"") | E13: =IFERROR(Input_CF!E9/Input_SFP!E3,"") | F13: =1 | G13: =IF(OR(C13="",ISBLANK(C13)),"NO DATA",IF(ABS(C13-1)<0.0001,"OK","Perlu rekonsiliasi"))

Sheet CommonSize_Trend
A1: COMMON SIZE & TREND 3 TAHUN
A2: Metric | B2: CY | C2: PY | D2: PPY | E2: Growth CY vs PY | F2: Share / ratio CY | G2: Share / ratio PY | H2: Comment
A3: Total assets | B3: =Input_SFP!C18 | C3: =Input_SFP!D18 | D3: =Input_SFP!E18 | E3: =IFERROR((B3/C3)-1,"") | F3: =1 | G3: =1 | H3: Scale
A4: Total liabilities | B4: =Input_SFP!C26 | C4: =Input_SFP!D26 | D4: =Input_SFP!E26 | E4: =IFERROR((B4/C4)-1,"") | F4: =IFERROR(B4/Input_SFP!C18,"") | G4: =IFERROR(C4/Input_SFP!D18,"") | H4: Balance sheet share
A5: Total equity | B5: =Input_SFP!C34 | C5: =Input_SFP!D34 | D5: =Input_SFP!E34 | E5: =IFERROR((B5/C5)-1,"") | F5: =IFERROR(B5/Input_SFP!C18,"") | G5: =IFERROR(C5/Input_SFP!D18,"") | H5: Capital base
A6: Profit for the year | B6: =Input_PL_OCI!C16 | C6: =Input_PL_OCI!D16 | D6: =Input_PL_OCI!E16 | E6: =IFERROR((B6/C6)-1,"") | F6: =IFERROR(B6/Input_SFP!C34,"") | G6: =IFERROR(C6/Input_SFP!D34,"") | H6: ROE cross-check
A7: Comprehensive income | B7: =Input_PL_OCI!C21 | C7: =Input_PL_OCI!D21 | D7: =Input_PL_OCI!E21 | E7: =IFERROR((B7/C7)-1,"") | F7: =IFERROR(B7/Input_SFP!C34,"") | G7: =IFERROR(C7/Input_SFP!D34,"") | H7: OCI volatility
A8: Cash / assets | B8: =IFERROR(Input_SFP!C3/Input_SFP!C18,"") | C8: =IFERROR(Input_SFP!D3/Input_SFP!D18,"") | D8: =IFERROR(Input_SFP!E3/Input_SFP!E18,"") | E8: =IFERROR((B8/C8)-1,"") | F8: =B8 | G8: =C8 | H8: Liquidity
A9: Investments / assets | B9: =IFERROR((Input_SFP!C5+Input_SFP!C6+Input_SFP!C7+Input_SFP!C8)/Input_SFP!C18,"") | C9: =IFERROR((Input_SFP!D5+Input_SFP!D6+Input_SFP!D7+Input_SFP!D8)/Input_SFP!D18,"") | D9: =IFERROR((Input_SFP!E5+Input_SFP!E6+Input_SFP!E7+Input_SFP!E8)/Input_SFP!E18,"") | E9: =IFERROR((B9/C9)-1,"") | F9: =B9 | G9: =C9 | H9: Investment intensity
A10: Insurance liabilities / total liabilities | B10: =IFERROR(Input_SFP!C19/Input_SFP!C26,"") | C10: =IFERROR(Input_SFP!D19/Input_SFP!D26,"") | D10: =IFERROR(Input_SFP!E19/Input_SFP!E26,"") | E10: =IFERROR((B10/C10)-1,"") | F10: =B10 | G10: =C10 | H10: Technical liability share
A11: CSM / equity | B11: =IFERROR(Input_IFRS17_Detail!C31,"") | C11: =IFERROR(Input_IFRS17_Detail!D31,"") | D11: =IFERROR(Input_IFRS17_Detail!E31,"") | E11: =IFERROR((B11/C11)-1,"") | F11: =B11 | G11: =C11 | H11: Future profit buffer

Sheet IFRS17_Analysis
A1: IFRS 17 / PSAK 117 ANALYSIS – LIFE
A2: Focus area | B2: Metric | C2: CY | D2: PY | E2: PPY | F2: Interpretation | G2: Flag | H2: Comment
A3: Service result | B3: Insurance service result | C3: =Input_IFRS17_Detail!C9 | D3: =Input_IFRS17_Detail!D9 | E3: =Input_IFRS17_Detail!E9 | F3: =IF(C3>=0,"Positif","Tertekan") | G3: =IF(C3>=0,"OK","Watch") | H3: Core service margin
A4: Finance result | B4: Insurance result after finance | C4: =Input_IFRS17_Detail!C12 | D4: =Input_IFRS17_Detail!D12 | E4: =Input_IFRS17_Detail!E12 | F4: =IF(C4>=0,"Positif","Tertekan") | G4: =IF(C4>=0,"OK","Watch") | H4: After finance
A5: Contract liabilities | B5: Insurance contract liabilities | C5: =Input_IFRS17_Detail!C13 | D5: =Input_IFRS17_Detail!D13 | E5: =Input_IFRS17_Detail!E13 | F5: =IF(C5>0,"Material","") | G5: Info | H5: Scale
A6: Risk adjustment | B6: RA / LIC | C6: =IFERROR(Input_IFRS17_Detail!C19/Input_IFRS17_Detail!C17,"") | D6: =IFERROR(Input_IFRS17_Detail!D19/Input_IFRS17_Detail!D17,"") | E6: =IFERROR(Input_IFRS17_Detail!E19/Input_IFRS17_Detail!E17,"") | F6: Coverage of non-financial risk | G6: Info
A7: CSM | B7: Closing CSM | C7: =Input_IFRS17_Detail!C26 | D7: =Input_IFRS17_Detail!D26 | E7: =Input_IFRS17_Detail!E26 | F7: =IF(C7="","No data",IF(C7>0,"Ada buffer CSM","Tidak ada buffer CSM")) | G7: =IF(C7="","NO DATA",IF(C7>0,"OK","Watch")) | H7: Unearned profit
A8: CSM | B8: CSM / equity | C8: =Input_IFRS17_Detail!C33 | D8: =Input_IFRS17_Detail!D33 | E8: =Input_IFRS17_Detail!E33 | F8: =IF(C8="","No data",IF(C8>=Setup!B25,"Memadai","Tipis")) | G8: =IF(C8="","NO DATA",IF(C8>=Setup!B25,"OK","Watch")) | H8: Capital support
A9: Claims | B9: Derived claim ratio | C9: =Input_IFRS17_Detail!C34 | D9: =Input_IFRS17_Detail!D34 | E9: =Input_IFRS17_Detail!E34 | F9: =IF(C9="","No data",IF(C9<=Setup!B17,"Terkendali","Tinggi")) | G9: =IF(C9="","NO DATA",IF(C9<=Setup!B17,"OK","Watch")) | H9: Claims and benefits / revenue
A10: Reinsurance | B10: Cession ratio | C10: =Input_IFRS17_Detail!C31 | D10: =Input_IFRS17_Detail!D31 | E10: =Input_IFRS17_Detail!E31 | F10: =IF(C10<=Setup!B27,"Cession moderat","Ketergantungan reasuransi relatif tinggi") | G10: =IF(C10<=Setup!B27,"OK","Watch") | H10: If disclosed

Sheet IFRS9_Analysis
A1: IFRS 9 / PSAK 109 ANALYSIS
A2: Focus area | B2: Metric | C2: CY | D2: PY | E2: PPY | F2: Interpretation | G2: Flag | H2: Comment
A3: Classification | B3: FVTPL share | C3: =IFERROR(Input_IFRS9_Detail!C3/(Input_IFRS9_Detail!C3+Input_IFRS9_Detail!C4+Input_IFRS9_Detail!C5+Input_IFRS9_Detail!C6),"") | D3: =IFERROR(Input_IFRS9_Detail!D3/(Input_IFRS9_Detail!D3+Input_IFRS9_Detail!D4+Input_IFRS9_Detail!D5+Input_IFRS9_Detail!D6),"") | E3: =IFERROR(Input_IFRS9_Detail!E3/(Input_IFRS9_Detail!E3+Input_IFRS9_Detail!E4+Input_IFRS9_Detail!E5+Input_IFRS9_Detail!E6),"") | F3: Porsi aset pada FVTPL | G3: Info
A4: Classification | B4: FVOCI share | C4: =IFERROR((Input_IFRS9_Detail!C4+Input_IFRS9_Detail!C5)/(Input_IFRS9_Detail!C3+Input_IFRS9_Detail!C4+Input_IFRS9_Detail!C5+Input_IFRS9_Detail!C6),"") | D4: =IFERROR((Input_IFRS9_Detail!D4+Input_IFRS9_Detail!D5)/(Input_IFRS9_Detail!D3+Input_IFRS9_Detail!D4+Input_IFRS9_Detail!D5+Input_IFRS9_Detail!D6),"") | E4: =IFERROR((Input_IFRS9_Detail!E4+Input_IFRS9_Detail!E5)/(Input_IFRS9_Detail!E3+Input_IFRS9_Detail!E4+Input_IFRS9_Detail!E5+Input_IFRS9_Detail!E6),"") | F4: Porsi OCI volatility | G4: Info
A5: ECL | B5: Coverage | C5: =Input_IFRS9_Detail!C16 | D5: =Input_IFRS9_Detail!D16 | E5: =Input_IFRS9_Detail!E16 | F5: =IF(C5>=Setup!B21,"Memadai","Tipis / perlu review") | G5: =IF(C5>=Setup!B21,"OK","Watch") | H5: Allowance / ECL assets
A6: ECL | B6: Stage 2+3 ratio | C6: =IFERROR((Input_IFRS9_Detail!C10+Input_IFRS9_Detail!C11)/Input_IFRS9_Detail!C8,"") | D6: =IFERROR((Input_IFRS9_Detail!D10+Input_IFRS9_Detail!D11)/Input_IFRS9_Detail!D8,"") | E6: =IFERROR((Input_IFRS9_Detail!E10+Input_IFRS9_Detail!E11)/Input_IFRS9_Detail!E8,"") | F6: =IF(C6<=Setup!B22,"Relatif baik","Migrasi risiko kredit naik") | G6: =IF(C6<=Setup!B22,"OK","Watch") | H6: Stage 2+3 / base
A7: Quality | B7: Credit-impaired / ECL base | C7: =IFERROR(Input_IFRS9_Detail!C18/Input_IFRS9_Detail!C8,"") | D7: =IFERROR(Input_IFRS9_Detail!D18/Input_IFRS9_Detail!D8,"") | E7: =IFERROR(Input_IFRS9_Detail!E18/Input_IFRS9_Detail!E8,"") | F7: Credit-impaired intensity | G7: Info
A8: P/L | B8: Portfolio yield | C8: =Input_IFRS9_Detail!C25 | D8: =Input_IFRS9_Detail!D25 | E8: =Input_IFRS9_Detail!E25 | F8: =IF(C8>=Setup!B26,"Memadai","Rendah") | G8: =IF(C8>=Setup!B26,"OK","Watch") | H8: Investment income / avg assets
A9: OCI | B9: FVOCI reserve closing | C9: =Input_IFRS9_Detail!C21 | D9: =Input_IFRS9_Detail!D21 | E9: =Input_IFRS9_Detail!E21 | F9: OCI reserve level | G9: Info
A10: Sensitivity | B10: Interest rate duration | C10: =Input_IFRS9_Detail!C26 | D10: =Input_IFRS9_Detail!D26 | E10: =Input_IFRS9_Detail!E26 | F10: Interest-rate sensitivity | G10: Info

Sheet Scorecard
A1: SCORECARD & EARLY WARNING
A2: Metric | B2: CY | C2: Threshold | D2: Pass? | E2: Points | F2: Comment
A3: ROE | B3: =Rasio!C4 | C3: >=Setup!B16 | D3: =IF(OR(B3="",ISBLANK(B3)),"No data",IF(B3>=Setup!B16,"Yes","No")) | E3: =IF(D3="Yes",12.5,0) | F3: =IF(D3="No data","No data",IF(D3="Yes","Within threshold","Check metric"))
A4: Cash / liabilities | B4: =Rasio!C6 | C4: >=Setup!B13 | D4: =IF(OR(B4="",ISBLANK(B4)),"No data",IF(B4>=Setup!B13,"Yes","No")) | E4: =IF(D4="Yes",12.5,0) | F4: =IF(D4="No data","No data",IF(D4="Yes","Within threshold","Check metric"))
A5: Liabilities / equity | B5: =Rasio!C5 | C5: <=Setup!B14 | D5: =IF(OR(B5="",ISBLANK(B5)),"No data",IF(B5<=Setup!B14,"Yes","No")) | E5: =IF(D5="Yes",12.5,0) | F5: =IF(D5="No data","No data",IF(D5="Yes","Within threshold","Check metric"))
A6: Claim ratio | B6: =Rasio!C7 | C6: <=Setup!B17 | D6: =IF(OR(B6="",ISBLANK(B6)),"No data",IF(B6<=Setup!B17,"Yes","No")) | E6: =IF(D6="Yes",12.5,0) | F6: =IF(D6="No data","No data",IF(D6="Yes","Within threshold","Check metric"))
A7: CSM / equity | B7: =Rasio!C8 | C7: >=Setup!B25 | D7: =IF(OR(B7="",ISBLANK(B7)),"No data",IF(B7>=Setup!B25,"Yes","No")) | E7: =IF(D7="Yes",12.5,0) | F7: =IF(D7="No data","No data",IF(D7="Yes","Within threshold","Check metric"))
A8: ECL coverage | B8: =Rasio!C10 | C8: >=Setup!B21 | D8: =IF(OR(B8="",ISBLANK(B8)),"No data",IF(B8>=Setup!B21,"Yes","No")) | E8: =IF(D8="Yes",12.5,0) | F8: =IF(D8="No data","No data",IF(D8="Yes","Within threshold","Check metric"))
A9: Stage 2+3 ratio | B9: =Rasio!C11 | C9: <=Setup!B22 | D9: =IF(OR(B9="",ISBLANK(B9)),"No data",IF(B9<=Setup!B22,"Yes","No")) | E9: =IF(D9="Yes",12.5,0) | F9: =IF(D9="No data","No data",IF(D9="Yes","Within threshold","Check metric"))
A10: OCF / profit | B10: =Rasio!C12 | C10: >=Setup!B23 | D10: =IF(OR(B10="",ISBLANK(B10)),"No data",IF(B10>=Setup!B23,"Yes","No")) | E10: =IF(D10="Yes",12.5,0) | F10: =IF(D10="No data","No data",IF(D10="Yes","Within threshold","Check metric"))
A12: Total score | B12: =SUM(E3:E10)
A13: Rating | B13: =IF(B12>=87.5,"Strong",IF(B12>=62.5,"Adequate","Weak"))
A15: Early warning | B15: =TEXTJOIN("; ",TRUE,IF(D3:D10="No",A3:A10,""))

Sheet Auto_Analysis
A1: RINGKASAN OTOMATIS / EXECUTIVE SUMMARY
A3: Perusahaan | B3: =Setup!B4
A4: Periode | B4: =Setup!B6
A6: Executive summary | B6: ="Perusahaan " & Setup!B4 & " dianalisis sebagai perusahaan asuransi jiwa pada periode " & Setup!B6 & ". ROE " & TEXT(Rasio!C4,"0.0%") & ", liabilities/equity " & TEXT(Rasio!C5,"0.00x") & ", claim ratio " & TEXT(Rasio!C7,"0.0%") & ", dan CSM/equity " & TEXT(Rasio!C8,"0.0%") & ". " & IF(Scorecard!B13="Strong","Profil keseluruhan kuat.",IF(Scorecard!B13="Adequate","Profil keseluruhan memadai dengan beberapa area review.","Profil keseluruhan lemah dan perlu perhatian intensif."))
A8: 1. Neraca | B8: ="Total aset " & TEXT(Input_SFP!C18,"#,##0") & ", total liabilitas " & TEXT(Input_SFP!C26,"#,##0") & ", dana peserta " & TEXT(Input_SFP!C27,"#,##0") & ", dan ekuitas " & TEXT(Input_SFP!C34,"#,##0") & "."
A9: 2. Hasil jasa | B9: ="Insurance service result " & TEXT(Input_IFRS17_Detail!C9,"#,##0") & " dan result setelah finance " & TEXT(Input_IFRS17_Detail!C12,"#,##0") & "."
A10: 3. CSM | B10: ="Closing CSM " & TEXT(Input_IFRS17_Detail!C26,"#,##0") & " atau " & TEXT(Input_IFRS17_Detail!C31,"0.0%") & " dari ekuitas."
A11: 4. Investasi | B11: ="Net investment result " & TEXT(Input_PL_OCI!C7,"#,##0") & ", portfolio yield " & TEXT(Input_IFRS9_Detail!C25,"0.0%") & "."
A12: 5. Kas & kualitas laba | B12: ="Operating cash flow " & TEXT(Input_CF!C3,"#,##0") & " dan OCF/profit " & TEXT(Rasio!C12,"0.0%") & "."
A13: 6. Early warning | B13: =Scorecard!B15

Sheet Dashboard
A1: DASHBOARD RINGKAS – ASURANSI JIWA IFRS 9 / IFRS 17
A3: Total Aset | B3: =Input_SFP!C18 | D3: Total Liabilitas | E3: =Input_SFP!C26 | G3: Total Ekuitas | H3: =Input_SFP!C34
A5: Profit Tahun Berjalan | B5: =Input_PL_OCI!C16 | D5: Comprehensive Income | E5: =Input_PL_OCI!C21 | G5: Score | H5: =Scorecard!B12
A8: Key ratios
A9: ROE | B9: =Rasio!C4 | C9: Liab/Equity | D9: =Rasio!C5 | E9: Claim ratio | F9: =Rasio!C7 | G9: CSM/Equity | H9: =Rasio!C8 | I9: OCF/Profit | J9: =Rasio!C12
A12: Executive summary | F12: Early warning
A13: =Auto_Analysis!B6 | F13: =Scorecard!B15

Sheet Validasi
A1: VALIDASI INPUT, KONSISTENSI, DAN KONTROL
A2: Kontrol | B2: Hasil | C2: Status | D2: Sheet | E2: Tindak lanjut | F2: Catatan
A3: Total assets = liabilities + funds + equity | B3: =IF(Input_SFP!C18=0,"NO DATA",IF(ABS(Input_SFP!C18-Input_SFP!C35)<1,"OK","CEK")) | C3: =B3 | D3: Input_SFP | E3: Pastikan neraca balance
A4: Cash ending CF = cash SFP | B4: =IF(Input_SFP!C3=0,"NO DATA",IF(ABS(Input_CF!C9-Input_SFP!C3)<1,"OK","CEK")) | C4: =B4 | D4: Input_CF/Input_SFP | E4: Rekonsiliasi ending cash
A5: Profit + OCI = total comprehensive | B5: =IF(AND(Input_PL_OCI!C16=0,Input_PL_OCI!C20=0),"NO DATA",IF(ABS(Input_PL_OCI!C21-(Input_PL_OCI!C16+Input_PL_OCI!C20))<1,"OK","CEK")) | C5: =B5 | D5: Input_PL_OCI | E5: Periksa laba dan OCI
A6: CF net increase helper | B6: =IF(AND(Input_CF!C3=0,Input_CF!C4=0,Input_CF!C5=0,Input_CF!C6=0),"NO DATA",IF(ABS(Input_CF!C7-SUM(Input_CF!C3:C6))<1,"OK","CEK")) | C6: =B6 | D6: Input_CF | E6: Periksa rekonsiliasi kas
A7: IFRS 9 total ECL base | B7: =IF(Input_IFRS9_Detail!C8=0,"NO DATA",IF(ABS(Input_IFRS9_Detail!C8-SUM(Input_IFRS9_Detail!C9:C11))<1,"OK","CEK")) | C7: =B7 | D7: Input_IFRS9_Detail | E7: Periksa klasifikasi aset
A8: IFRS 9 total allowance | B8: =IF(Input_IFRS9_Detail!C15=0,"NO DATA",IF(ABS(Input_IFRS9_Detail!C15-SUM(Input_IFRS9_Detail!C12:C14))<1,"OK","CEK")) | C8: =B8 | D8: Input_IFRS9_Detail | E8: Periksa allowance
A9: IFRS17 life service result | B9: =IF(Input_IFRS17_Detail!C3=0,"NO DATA",IF(ABS(Input_IFRS17_Detail!C9-(Input_IFRS17_Detail!C3-Input_IFRS17_Detail!C4-Input_IFRS17_Detail!C5-Input_IFRS17_Detail!C6-Input_IFRS17_Detail!C7+Input_IFRS17_Detail!C8))<1,"OK","CEK")) | C9: =B9 | D9: Input_IFRS17_Detail | E9: Periksa hasil jasa asuransi
A10: Closing CSM helper | B10: =IF(Input_IFRS17_Detail!C26="","NO DATA",IF(ABS(Input_IFRS17_Detail!C26-(Input_IFRS17_Detail!C20+Input_IFRS17_Detail!C21+Input_IFRS17_Detail!C22+Input_IFRS17_Detail!C23-Input_IFRS17_Detail!C24+Input_IFRS17_Detail!C25))<1,"OK","CEK")) | C10: =B10 | D10: Input_IFRS17_Detail | E10: Periksa pergerakan CSM
A11: RAW CY data populated | B11: =IF((COUNT(Raw_SFP!C:C)+COUNT(Raw_PL_OCI!C:C)+COUNT(Raw_CF!C:C)+COUNT(Raw_IFRS17!C:C)+COUNT(Raw_IFRS9!C:C))=0,"NO DATA","OK") | C11: =B11 | D11: All RAW sheets | E11: Pastikan minimal data CY terisi sebelum menarik kesimpulan.

Sheet Equity_Research
A1: EQUITY RESEARCH STYLE – ASURANSI JIWA
A2: Section | B2: Narasi / Output otomatis
A3: Investment thesis | B3: ="Perusahaan " & Setup!B4 & " pada " & Setup!B6 & " membukukan ROE " & TEXT(Rasio!C4,"0.0%") & ", leverage " & TEXT(Rasio!C5,"0.00x") & ", claim ratio " & TEXT(Rasio!C7,"0.0%") & ", dan CSM/equity " & TEXT(Rasio!C8,"0.0%") & ". Secara keseluruhan profil dinilai " & Scorecard!B13 & " berdasarkan score " & TEXT(Scorecard!B12,"0.0") & "."
A4: Capital & balance sheet | B4: ="Total aset " & TEXT(Input_SFP!C18,"#,##0") & ", total liabilitas " & TEXT(Input_SFP!C26,"#,##0") & ", dan ekuitas " & TEXT(Input_SFP!C34,"#,##0") & ". Leverage " & TEXT(Rasio!C5,"0.00x") & IF(Rasio!C5<=Setup!B14,", masih dalam batas internal.",", berada di atas ambang yang perlu diwaspadai.")
A5: Insurance franchise | B5: ="Insurance service result sebesar " & TEXT(Input_IFRS17_Detail!C9,"#,##0") & " dan insurance result after finance sebesar " & TEXT(Input_IFRS17_Detail!C12,"#,##0") & ". Ini menunjukkan " & IF(Input_IFRS17_Detail!C12>=0,"franchise profit setelah finance masih positif.","hasil jasa/finance masih tertekan.")
A6: CSM & future earnings | B6: ="Closing CSM sebesar " & TEXT(Input_IFRS17_Detail!C26,"#,##0") & " atau " & TEXT(Rasio!C8,"0.0%") & " dari ekuitas. " & IF(Rasio!C8>=Setup!B25,"Buffer laba masa depan terlihat memadai.","Buffer laba masa depan terlihat tipis dibanding ekuitas.")
A7: Investment quality | B7: ="Portfolio yield " & TEXT(Input_IFRS9_Detail!C25,"0.0%") & ", ECL coverage " & TEXT(Rasio!C10,"0.000%") & ", dan Stage 2+3 ratio " & TEXT(Rasio!C11,"0.0%") & ". " & IF(AND(Rasio!C10>=Setup!B21,Rasio!C11<=Setup!B22),"Profil IFRS 9 relatif bersih.","Portofolio investasi perlu pengawasan kualitas kredit yang lebih dekat.")
A8: Cash conversion | B8: ="Operating cash flow sebesar " & TEXT(Input_CF!C3,"#,##0") & " dengan OCF/profit " & TEXT(Rasio!C12,"0.0%") & ". " & IF(Rasio!C12>=Setup!B23,"Laba relatif terkonversi menjadi kas.","Kualitas laba perlu dicermati karena konversi kas lemah.")
A9: Analytical stance | B9: =IF(AND(Scorecard!B13="Strong",Rasio!C12>=1,Rasio!C8>=Setup!B25),"Stance analitis: constructive. Mesin laba masa depan masih ditopang CSM dan kas memadai.",IF(Scorecard!B13="Adequate","Stance analitis: selective. Fundamental inti memadai namun ada area review yang perlu dipantau.","Stance analitis: cautious. Perlu perhatian pada kualitas laba, leverage, atau penyangga IFRS 17."))

Sheet Regulatory_Flags
A1: REGULATORY RED FLAGS – ASURANSI JIWA
A2: Area | B2: Metric CY | C2: Threshold | D2: Severity | E2: Status | F2: Implikasi pengawas | G2: Narasi
A3: Likuiditas | B3: =Rasio!C6 | C3: =Setup!B13 | D3: =IF(B3>=C3,"Low",IF(B3>=C3*0.75,"Medium","High")) | E3: =IF(D3="Low","OK","Watch") | F3: =IF(D3="High","Kapasitas memenuhi kewajiban jangka pendek perlu dicermati.","Pantau likuiditas operasional dan penempatan kas.") | G3: =IF(D3="Low","Cash/liabilities masih memadai.","Likuiditas relatif tipis versus kewajiban.")
A4: Leverage | B4: =Rasio!C5 | C4: =Setup!B14 | D4: =IF(B4<=C4,"Low",IF(B4<=C4*1.2,"Medium","High")) | E4: =IF(D4="Low","OK","Watch") | F4: =IF(D4="High","Leverage tinggi dapat menekan fleksibilitas permodalan.","Pastikan struktur modal dan buffer solvabilitas memadai.") | G4: =IF(D4="Low","Leverage masih dalam parameter.","Rasio liabilitas terhadap ekuitas perlu perhatian.")
A5: Claim burden | B5: =Rasio!C7 | C5: =Setup!B17 | D5: =IF(B5<=C5,"Low",IF(B5<=C5*1.15,"Medium","High")) | E5: =IF(D5="Low","OK","Watch") | F5: =IF(D5="High","Tingginya claim ratio dapat menggerus future service margin.","Pantau profitabilitas produk dan repricing.") | G5: =IF(D5="Low","Claim ratio masih terkendali.","Claim ratio relatif tinggi dan dapat menekan profitabilitas.")
A6: CSM buffer | B6: =Rasio!C8 | C6: =Setup!B25 | D6: =IF(B6>=C6,"Low",IF(B6>=C6*0.75,"Medium","High")) | E6: =IF(D6="Low","OK","Watch") | F6: =IF(D6="High","Buffer laba masa depan tipis; sensitivitas terhadap asumsi lebih tinggi.","Perlu review granularitas portofolio dan onerous contracts.") | G6: =IF(D6="Low","CSM masih menjadi penyangga laba masa depan.","CSM/equity tipis sehingga kualitas laba masa depan perlu diawasi.")
A7: Reinsurance cession | B7: =Rasio!C9 | C7: =Setup!B27 | D7: =IF(B7<=C7,"Low",IF(B7<=C7*1.2,"Medium","High")) | E7: =IF(D7="Low","OK","Watch") | F7: =IF(D7="High","Ketergantungan reasuransi dapat memperbesar risiko counterparty dan earnings volatility.","Pantau kualitas reinsurer dan terms treaty.") | G7: =IF(D7="Low","Ketergantungan reasuransi masih moderat.","Cession ratio relatif tinggi dan perlu ditelaah.")
A8: IFRS 9 credit | B8: =Rasio!C11 | C8: =Setup!B22 | D8: =IF(B8<=C8,"Low",IF(B8<=C8*1.5,"Medium","High")) | E8: =IF(D8="Low","OK","Watch") | F8: =IF(D8="High","Migrasi Stage 2/3 menunjukkan risiko kredit portofolio meningkat.","Perlu review konsentrasi aset dan ECL assumptions.") | G8: =IF(D8="Low","Stage 2+3 ratio rendah.","Portofolio kredit menunjukkan migrasi risiko yang perlu pengawasan.")
A9: Cash conversion | B9: =Rasio!C12 | C9: =Setup!B23 | D9: =IF(B9>=C9,"Low",IF(B9>=C9*0.7,"Medium","High")) | E9: =IF(D9="Low","OK","Watch") | F9: =IF(D9="High","Laba yang tidak didukung kas dapat menurunkan kualitas earnings.","Perlu rekonsiliasi sumber laba dan working capital/claims timing.") | G9: =IF(D9="Low","Konversi laba ke kas cukup baik.","OCF/profit lemah dan kualitas laba perlu ditelaah.")

Sheet Underwriting_Quality
A1: UNDERWRITING QUALITY – ASURANSI JIWA
A2: Fokus | B2: CY | C2: PY | D2: Benchmark | E2: Assessment | F2: Narasi
A3: Service margin | B3: =IFERROR(Input_IFRS17_Detail!C9/Input_IFRS17_Detail!C3,"") | C3: =IFERROR(Input_IFRS17_Detail!D9/Input_IFRS17_Detail!D3,"") | D3: >=0 | E3: =IF(B3>=0,"Positif","Negatif") | F3: =IF(B3>=0,"Hasil jasa inti masih positif terhadap revenue.","Service margin negatif; profit inti tertekan.")
A4: Claim ratio | B4: =Rasio!C7 | C4: =Rasio!D7 | D4: =Setup!B17 | E4: =IF(B4<=D4,"Baik","Tinggi") | F4: =IF(B4<=D4,"Beban klaim relatif terkendali.","Beban klaim relatif tinggi terhadap insurance revenue.")
A5: CSM / equity | B5: =Rasio!C8 | C5: =Rasio!D8 | D5: =Setup!B25 | E5: =IF(B5>=D5,"Kuat","Tipis") | F5: =IF(B5>=D5,"Penyangga laba masa depan relatif kuat.","Buffer CSM relatif tipis sehingga sensitivitas asumsi naik.")
A6: RA / LIC | B6: =IFERROR(Input_IFRS17_Detail!C19/Input_IFRS17_Detail!C17,"") | C6: =IFERROR(Input_IFRS17_Detail!D19/Input_IFRS17_Detail!D17,"") | D6: n/a | E6: Informasional | F6: ="Risk adjustment sebesar " & TEXT(B6,"0.0%") & " dari LIC."
A7: Cession ratio | B7: =Rasio!C9 | C7: =Rasio!D9 | D7: =Setup!B27 | E7: =IF(B7<=D7,"Moderat","Tinggi") | F7: =IF(B7<=D7,"Penggunaan reasuransi masih moderat.","Ketergantungan reasuransi perlu ditinjau lebih lanjut.")
A8: Finance drag | B8: =IFERROR((Input_IFRS17_Detail!C12-Input_IFRS17_Detail!C9)/Input_IFRS17_Detail!C3,"") | C8: =IFERROR((Input_IFRS17_Detail!D12-Input_IFRS17_Detail!D9)/Input_IFRS17_Detail!D3,"") | D8: >=-5% | E8: =IF(B8>=-0.05,"Terkendali","Tertekan") | F8: =IF(B8>=-0.05,"Dampak finance terhadap hasil jasa masih terkendali.","Dampak finance menekan profit IFRS 17 secara material.")

Sheet Reserve_Quality
A1: RESERVE QUALITY – ASURANSI JIWA
A2: Fokus | B2: CY | C2: PY | D2: Assessment | E2: Flag | F2: Narasi
A3: Insurance contract liabilities | B3: =Input_IFRS17_Detail!C13 | C3: =Input_IFRS17_Detail!D13 | D3: Informasional | E3: Info | F3: ="Total insurance contract liabilities sebesar " & TEXT(B3,"#,##0") & "."
A4: LRC share | B4: =IFERROR(Input_IFRS17_Detail!C16/Input_IFRS17_Detail!C13,"") | C4: =IFERROR(Input_IFRS17_Detail!D16/Input_IFRS17_Detail!D13,"") | D4: =IF(B4>=0.5,"Dominan future service","Dominan incurred claims") | E4: Info | F4: ="LRC mencakup " & TEXT(B4,"0.0%") & " dari insurance contract liabilities."
A5: LIC share | B5: =IFERROR(Input_IFRS17_Detail!C17/Input_IFRS17_Detail!C13,"") | C5: =IFERROR(Input_IFRS17_Detail!D17/Input_IFRS17_Detail!D13,"") | D5: Informasional | E5: Info | F5: ="LIC mencakup " & TEXT(B5,"0.0%") & " dari insurance contract liabilities."
A6: Loss component / liabilities | B6: =IFERROR(Input_IFRS17_Detail!C18/Input_IFRS17_Detail!C13,"") | C6: =IFERROR(Input_IFRS17_Detail!D18/Input_IFRS17_Detail!D13,"") | D6: =IF(B6<=0.05,"Rendah","Perlu review") | E6: =IF(B6<=0.05,"OK","Watch") | F6: =IF(B6<=0.05,"Porsi onerous/loss component masih rendah.","Loss component relatif material dan perlu ditelaah per cohort.")
A7: RA / LIC | B7: =IFERROR(Input_IFRS17_Detail!C19/Input_IFRS17_Detail!C17,"") | C7: =IFERROR(Input_IFRS17_Detail!D19/Input_IFRS17_Detail!D17,"") | D7: Informasional | E7: Info | F7: ="Risk adjustment setara " & TEXT(B7,"0.0%") & " dari LIC."
A8: CSM buffer / liabilities | B8: =IFERROR(Input_IFRS17_Detail!C26/Input_IFRS17_Detail!C13,"") | C8: =IFERROR(Input_IFRS17_Detail!D26/Input_IFRS17_Detail!D13,"") | D8: =IF(B8>=0.1,"Baik","Tipis") | E8: =IF(B8>=0.1,"OK","Watch") | F8: =IF(B8>=0.1,"CSM memberi penyangga laba masa depan yang terlihat memadai.","CSM relatif kecil dibanding liabilitas kontrak.")

Sheet Reinsurance_Dependence
A1: REINSURANCE DEPENDENCE – ASURANSI JIWA
A2: Fokus | B2: CY | C2: PY | D2: Assessment | E2: Flag | F2: Narasi
A3: Reinsurance asset / equity | B3: =IFERROR(Input_IFRS17_Detail!C14/Input_SFP!C34,"") | C3: =IFERROR(Input_IFRS17_Detail!D14/Input_SFP!D34,"") | D3: =IF(B3<=0.5,"Rendah","Meningkat") | E3: =IF(B3<=0.5,"OK","Watch") | F3: ="Reinsurance asset setara " & TEXT(B3,"0.0%") & " dari ekuitas."
A4: Cession ratio | B4: =Rasio!C9 | C4: =Rasio!D9 | D4: =IF(B4<=Setup!B27,"Moderat","Tinggi") | E4: =IF(B4<=Setup!B27,"OK","Watch") | F4: =IF(B4<=Setup!B27,"Ketergantungan reasuransi masih moderat.","Ketergantungan reasuransi relatif tinggi.")
A5: Reinsurance result / revenue | B5: =IFERROR(ABS(Input_IFRS17_Detail!C8)/Input_IFRS17_Detail!C3,"") | C5: =IFERROR(ABS(Input_IFRS17_Detail!D8)/Input_IFRS17_Detail!D3,"") | D5: Informasional | E5: Info | F5: ="Beban/(pendapatan) reasuransi setara " & TEXT(B5,"0.0%") & " dari insurance revenue."
A6: Reinsurance liabilities / reinsurance assets | B6: =IFERROR(Input_IFRS17_Detail!C15/MAX(Input_IFRS17_Detail!C14,1),"") | C6: =IFERROR(Input_IFRS17_Detail!D15/MAX(Input_IFRS17_Detail!D14,1),"") | D6: =IF(B6<=0.5,"Ringan","Perlu review") | E6: =IF(B6<=0.5,"OK","Watch") | F6: ="Reinsurance liabilities sebesar " & TEXT(B6,"0.0%") & " dari reinsurance assets."

Sheet Earnings_Quality
A1: EARNINGS QUALITY – ASURANSI JIWA
A2: Fokus | B2: CY | C2: PY | D2: Assessment | E2: Flag | F2: Narasi
A3: Profit for the year | B3: =Input_PL_OCI!C16 | C3: =Input_PL_OCI!D16 | D3: =IF(B3>=0,"Positif","Negatif") | E3: =IF(B3>=0,"OK","Watch") | F3: ="Laba tahun berjalan sebesar " & TEXT(B3,"#,##0") & "."
A4: OCI / profit | B4: =IFERROR(Input_PL_OCI!C20/MAX(ABS(Input_PL_OCI!C16),1),"") | C4: =IFERROR(Input_PL_OCI!D20/MAX(ABS(Input_PL_OCI!D16),1),"") | D4: =IF(ABS(B4)<=0.5,"Seimbang","Volatil") | E4: =IF(ABS(B4)<=0.5,"OK","Watch") | F4: ="OCI setara " & TEXT(B4,"0.0x") & " dari laba tahun berjalan."
A5: Service result / PBT | B5: =IFERROR(Input_IFRS17_Detail!C9/MAX(Input_PL_OCI!C14,1),"") | C5: =IFERROR(Input_IFRS17_Detail!D9/MAX(Input_PL_OCI!D14,1),"") | D5: =IF(B5>=0.5,"Core-driven","Non-core heavy") | E5: =IF(B5>=0.5,"OK","Watch") | F5: =IF(B5>=0.5,"Sebagian besar laba sebelum pajak ditopang hasil jasa.","Laba sebelum pajak lebih banyak ditopang item non-core / volatil.")
A6: Investment result / PBT | B6: =IFERROR(Input_PL_OCI!C7/MAX(Input_PL_OCI!C14,1),"") | C6: =IFERROR(Input_PL_OCI!D7/MAX(Input_PL_OCI!D14,1),"") | D6: Informasional | E6: Info | F6: ="Kontribusi hasil investasi setara " & TEXT(B6,"0.0x") & " dari laba sebelum pajak."
A7: OCF / profit | B7: =Rasio!C12 | C7: =Rasio!D12 | D7: =IF(B7>=Setup!B23,"Baik","Lemah") | E7: =IF(B7>=Setup!B23,"OK","Watch") | F7: =IF(B7>=Setup!B23,"Laba relatif terkover oleh kas operasi.","Kualitas laba perlu review karena kas operasi lemah.")

Sheet V5_Audit_Log
A1: Area | B1: Perubahan V5
A2: Formula/Control | B2: README ditambah catatan sign convention life insurance, CSM, ECL, validasi, dan scorecard V5.
A3: Formula/Control | B3: Raw_IFRS17 notes diperjelas untuk sign convention expense, reinsurance net result, dan CSM release.
A4: Formula/Control | B4: Input_IFRS17_Detail: service result, result after finance, closing CSM, CSM/equity, dan derived claim ratio diperbaiki.
A5: Formula/Control | B5: Input_IFRS9_Detail: ECL base direkonsiliasi ke Stage 1+2+3 dan denominator guard diperkuat.
A6: Formula/Control | B6: Input_PL_OCI ditambah catatan bridge ke IFRS17 service result.
A7: Formula/Control | B7: Rasio: status diperbaiki agar blank/no denominator menjadi NO DATA.
A8: Formula/Control | B8: Scorecard: no data tidak mendapat poin dan early warning hanya untuk metric yang gagal.
A9: Formula/Control | B9: Validasi: all-zero/blank data menjadi NO DATA; IFRS9 ECL, IFRS17 service result, dan closing CSM check diperbaiki.
A10: Formula/Control | B10: IFRS17_Analysis: interpretasi CSM dan claim ratio diberi NO DATA guard.
A11: Catatan | B11: Versi V5 memakai convention: revenue positif; claims/benefits, acquisition, other expense, onerous losses positif sebagai beban dan dikurangkan; reinsurance net result positif bila income/recovery dan negatif bila expense.
A12: Catatan | B12: Review judgement mapping tetap diperlukan terhadap audited financial statements, terutama produk jiwa yang menggunakan PAA/GMM/VFA dan treatment kontrak investasi.
